{
  "geocoded_waypoints": [
    {
      "geocoder_status": "OK",
      "place_id": "ChIJdd4hrwug2EcRmSrV3Vo6llI",
      "types": [ "locality", "political" ]
    },
    {
      "geocoder_status": "OK",
      "place_id": "ChIJmb1k2ko-eUgRqdwTAv26rVE",
      "types": [ "locality", "political" ]
    },
    {
      "geocoder_status": "OK",
      "place_id": "ChIJq7M964y4e0gRJ2XaINteiJo",
      "types": [ "locality", "political" ]
    },
    {
      "geocoder_status": "OK",
      "place_id": "ChIJ2_UmUkxNekgRqmv-BDgUvtk",
      "types": [ "locality", "political" ]
    }
  ],
  "routes": [
    {
      "bounds": {
        "northeast": {
          "lat": 53.8051112,
          "lng": -0.128012
        },
        "southwest": {
          "lat": 51.507309,
          "lng": -2.2879954
        }
      },
      "copyrights": "Map data ©2018 Google",
      "legs": [
        {
          "distance": {
            "text": "389 km",
            "value": 389021
          },
          "duration": {
            "text": "4 hours 59 mins",
            "value": 17945
          },
          "end_address": "Manchester, UK",
          "end_location": {
            "lat": 53.4807512,
            "lng": -2.2425604
          },
          "start_address": "London, UK",
          "start_location": {
            "lat": 51.507309,
            "lng": -0.128012
          },
          "steps": [
            {
              "distance": {
                "text": "0.3 km",
                "value": 322
              },
              "duration": {
                "text": "2 mins",
                "value": 91
              },
              "end_location": {
                "lat": 51.5072053,
                "lng": -0.1323652
              },
              "html_instructions": "Head <b>north-west</b> on <b>A4</b> towards <b>Spring Gardens</b><div style=\"font-size:0.9em\">Leaving toll zone in 220m at Pall Mall</div><div style=\"font-size:0.9em\">May be closed at certain times or on certain days</div>",
              "polyline": {
                "points": "u_kyH`_XIVCHEPEd@Ep@A\\CVUfEG`ACb@Cv@AH?H?H@J?H|@dD`@dB"
              },
              "start_location": {
                "lat": 51.507309,
                "lng": -0.128012
              },
              "travel_mode": "DRIVING"
            },
            {
              "distance": {
                "text": "0.1 km",
                "value": 122
              },
              "duration": {
                "text": "1 min",
                "value": 34
              },
              "end_location": {
                "lat": 51.5079418,
                "lng": -0.1332601
              },
              "html_instructions": "Turn <b>right</b> onto <b>Waterloo Pl</b><div style=\"font-size:0.9em\">May be closed at certain times or on certain days</div>",
              "maneuver": "turn-right",
              "polyline": {
                "points": "a_kyHhzXPl@KHOLk@d@A@A?A?C?CA}@v@OL"
              },
              "start_location": {
                "lat": 51.5072053,
                "lng": -0.1323652
              },
              "travel_mode": "DRIVING"
            },
            {
              "distance": {
                "text": "0.2 km",
                "value": 241
              },
              "duration": {
                "text": "1 min",
                "value": 86
              },
              "end_location": {
                "lat": 51.5098604,
                "lng": -0.1348551
              },
              "html_instructions": "Continue onto <b>Regent Street Saint James's</b><div style=\"font-size:0.9em\">Entering toll zone</div><div style=\"font-size:0.9em\">Leaving toll zone</div><div style=\"font-size:0.9em\">May be closed at certain times or on certain days</div>",
              "polyline": {
                "points": "sckyHz_YQJA?A?A?I?aBtA_CjB_Az@[Z_@X"
              },
              "start_location": {
                "lat": 51.5079418,
                "lng": -0.1332601
              },
              "travel_mode": "DRIVING"
            },
            {
              "distance": {
                "text": "1.8 km",
                "value": 1794
              },
              "duration": {
                "text": "8 mins",
                "value": 505
              },
              "end_location": {
                "lat": 51.5228905,
                "lng": -0.1462494
              },
              "html_instructions": "Continue onto <b>Regent St</b>/<b>A4201</b><div style=\"font-size:0.9em\">Continue to follow A4201</div><div style=\"font-size:0.9em\">Entering toll zone</div><div style=\"font-size:0.9em\">Leaving toll zone in 1.2 km</div><div style=\"font-size:0.9em\">Entering toll zone in 1.2 km</div>",
              "polyline": {
                "points": "sokyHziYUTEDA@ABAB?@?BAB?B?@?B?B?DDPFZDXDRBVD\\?B@L?J@P?|@?l@AZAVANADC^G`@EPKj@IVKTMXILILIFIJmAfA[VML}ApACBIHOJSPq@l@OJMJmAfAqBdBaAx@YVSPIH[V[XKFWPQH[Lm@Ng@L_@FUD_@HKB[DqAXIBQDE?C?E?iA`@gA\\WJSHgA^[JMFMFC@EBEDCBCDEDQd@ELAHADAF?BM^CHCJELCHEHIJEHKNGFIFKDKFMDyBx@k@TaAZuFjBwEzAqC|@UH"
              },
              "start_location": {
                "lat": 51.5098604,
                "lng": -0.1348551
              },
              "travel_mode": "DRIVING"
            },
            {
              "distance": {
                "text": "0.1 km",
                "value": 140
              },
              "duration": {
                "text": "1 min",
                "value": 42
              },
              "end_location": {
                "lat": 51.5234539,
                "lng": -0.1478573
              },
              "html_instructions": "Turn <b>left</b> onto <b>Park Cres</b>/<b>A4201</b>",
              "maneuver": "turn-left",
              "polyline": {
                "points": "aanyH`q[@L?P@H?N?N?RAPCVCNCPCLERKZKRINGHGHMNKHGBGB"
              },
              "start_location": {
                "lat": 51.5228905,
                "lng": -0.1462494
              },
              "travel_mode": "DRIVING"
            },
            {
              "distance": {
                "text": "0.3 km",
                "value": 326
              },
              "duration": {
                "text": "1 min",
                "value": 85
              },
              "end_location": {
                "lat": 51.5229778,
                "lng": -0.1524928
              },
              "html_instructions": "Turn <b>left</b> onto <b>Marylebone Rd</b>/<b>A501</b><div style=\"font-size:0.9em\">Leaving toll zone</div>",
              "maneuver": "turn-left",
              "polyline": {
                "points": "qdnyHb{[RtBDb@@PBN@V\\nH@f@BnA@RFjB@j@B|@Fv@"
              },
              "start_location": {
                "lat": 51.5234539,
                "lng": -0.1478573
              },
              "travel_mode": "DRIVING"
            },
            {
              "distance": {
                "text": "0.1 km",
                "value": 121
              },
              "duration": {
                "text": "1 min",
                "value": 46
              },
              "end_location": {
                "lat": 51.5240234,
                "lng": -0.1529632
              },
              "html_instructions": "Turn <b>right</b> onto <b>York Gate</b>",
              "maneuver": "turn-right",
              "polyline": {
                "points": "sanyH`x\\SHmBp@i@Pc@N"
              },
              "start_location": {
                "lat": 51.5229778,
                "lng": -0.1524928
              },
              "travel_mode": "DRIVING"
            },
            {
              "distance": {
                "text": "1.7 km",
                "value": 1671
              },
              "duration": {
                "text": "3 mins",
                "value": 200
              },
              "end_location": {
                "lat": 51.5340504,
                "lng": -0.1626657
              },
              "html_instructions": "Turn <b>left</b> onto <b>Outer Cir</b>/<b>Ulster Terrace</b><div style=\"font-size:0.9em\">Continue to follow Outer Cir</div>",
              "maneuver": "turn-left",
              "polyline": {
                "points": "chnyH~z\\TxB?D\\nDFf@Fr@Fl@?H@L?L?R?JAJAJCJEPERcClIg@dBWz@GPINGPGJIJEDGFEBIFIDGDMH]VURSPi@\\i@`@[VURONONGJW`@OTMRSb@iAvBe@|@SZGJ]n@iAvBsAbCe@|@Q\\S^i@bAGJGJIJ[^STQNMLq@X_@Ns@R_ATm@H_@@Q?SCQA[MWO[WsAkA{@u@KKAAUQ}AsA{AqAa@a@IKMM[]KQGMEI"
              },
              "start_location": {
                "lat": 51.5240234,
                "lng": -0.1529632
              },
              "travel_mode": "DRIVING"
            },
            {
              "distance": {
                "text": "1.2 km",
                "value": 1168
              },
              "duration": {
                "text": "3 mins",
                "value": 186
              },
              "end_location": {
                "lat": 51.5418251,
                "lng": -0.1736832
              },
              "html_instructions": "Turn <b>left</b> onto <b>Avenue Road</b>",
              "maneuver": "turn-left",
              "polyline": {
                "points": "yfpyHtw^aBlBQRQRSVMNGJ_@n@k@|@}@vAc@r@CBgCdEkAhBcAdBU^k@~@[f@m@jA[r@o@hBWr@CH_@bA_@fA}@nCQ`@_@f@i@n@ABKNYZu@t@CBy@t@mFtEa@XGNEH?@CHCPCJE`@"
              },
              "start_location": {
                "lat": 51.5340504,
                "lng": -0.1626657
              },
              "travel_mode": "DRIVING"
            },
            {
              "distance": {
                "text": "85 m",
                "value": 85
              },
              "duration": {
                "text": "1 min",
                "value": 15
              },
              "end_location": {
                "lat": 51.5417016,
                "lng": -0.1748888
              },
              "html_instructions": "Slight <b>left</b> onto <b>Adelaide Rd</b>/<b>A41</b>",
              "maneuver": "turn-slight-left",
              "polyline": {
                "points": "mwqyHn|`@Db@@\\Dz@JrB"
              },
              "start_location": {
                "lat": 51.5418251,
                "lng": -0.1736832
              },
              "travel_mode": "DRIVING"
            },
            {
              "distance": {
                "text": "0.2 km",
                "value": 151
              },
              "duration": {
                "text": "1 min",
                "value": 27
              },
              "end_location": {
                "lat": 51.5429638,
                "lng": -0.1750252
              },
              "html_instructions": "Turn <b>right</b> onto <b>Finchley Rd</b>/<b>A41</b>",
              "maneuver": "turn-right",
              "polyline": {
                "points": "svqyH`da@ER?DABABABCBEDABE?A@C@G?Q@uBYi@CM?O?"
              },
              "start_location": {
                "lat": 51.5417016,
                "lng": -0.1748888
              },
              "travel_mode": "DRIVING"
            },
            {
              "distance": {
                "text": "2.4 km",
                "value": 2437
              },
              "duration": {
                "text": "6 mins",
                "value": 371
              },
              "end_location": {
                "lat": 51.5591807,
                "lng": -0.1967841
              },
              "html_instructions": "Slight <b>left</b> to stay on <b>Finchley Rd</b>/<b>A41</b>",
              "maneuver": "turn-slight-left",
              "polyline": {
                "points": "o~qyH|da@WFM@_@BSB[BK@ODSFUJg@XYPWRYZa@f@ABA@OXS`@MZCFADELELOh@[fAEPELCJCNOd@_@pAM^ELKPEHCFORKNKJg@j@QNKJc@b@[XA?MJSNWPWReB|AsAnAGDQNMLGFUTQLEDIF]T]PA@IDg@VYLULQJIFKHSVCBIJMTSXEFq@lAwArC]p@EFGNSb@U^o@lAg@z@[f@oAvBSb@Q^Sh@GTI\\Gd@If@AHATKtAEl@Ed@Ef@If@Op@ENCJCHQh@_@x@]p@yBtEk@pAKTCFKRUb@KXcArBSf@OVA@A@GBUj@INkAfC[t@GLS`@[h@Ub@SXS\\g@p@QRSRORONGF_@XSLITA@A@WLUJaA^_A\\GBIBKGOF}@j@YTm@j@CJADGDUPOJ"
              },
              "start_location": {
                "lat": 51.5429638,
                "lng": -0.1750252
              },
              "travel_mode": "DRIVING"
            },
            {
              "distance": {
                "text": "2.3 km",
                "value": 2333
              },
              "duration": {
                "text": "4 mins",
                "value": 215
              },
              "end_location": {
                "lat": 51.57544,
                "lng": -0.2154607
              },
              "html_instructions": "Turn <b>left</b> onto <b>Hendon Way</b>/<b>A41</b><div style=\"font-size:0.9em\">Continue to follow A41</div>",
              "maneuver": "turn-left",
              "polyline": {
                "points": "{cuyHzle@AFABCDCBIDEDEDCBCFCFCJ?l@?h@?f@C`@Cb@C\\G`@E^Mt@oA~Fu@fDKj@_AbESz@Sp@KVITMZOXMTMNKNQR[XSLs@b@]PeAh@KDMFmCnA_@Ps@Zo@XoBx@}Al@_@NsAj@E@eAd@q@Xc@Re@Ta@TaAd@IBOH{@ZWJ]PWLULOF[Rw@d@_@T]TUNC@YTu@h@qB`BOLqBhBsC|CeCtCOPQRiD|DA@_AhAwA`BgAnAWZc@l@_@j@Yb@]n@S^ABUd@O\\OZABO^K\\O`@"
              },
              "start_location": {
                "lat": 51.5591807,
                "lng": -0.1967841
              },
              "travel_mode": "DRIVING"
            },
            {
              "distance": {
                "text": "0.1 km",
                "value": 133
              },
              "duration": {
                "text": "1 min",
                "value": 12
              },
              "end_location": {
                "lat": 51.5760845,
                "lng": -0.2170807
              },
              "html_instructions": "Take the <b>A406</b> slip road to <b>M1</b>/<b>Watford</b>/<b>Wood Green</b>/<b>Brent Cross</b>",
              "polyline": {
                "points": "oixyHrai@S~@Mh@Y|@cAzC"
              },
              "start_location": {
                "lat": 51.57544,
                "lng": -0.2154607
              },
              "travel_mode": "DRIVING"
            },
            {
              "distance": {
                "text": "0.5 km",
                "value": 495
              },
              "duration": {
                "text": "1 min",
                "value": 45
              },
              "end_location": {
                "lat": 51.5738052,
                "lng": -0.2220568
              },
              "html_instructions": "Keep <b>right</b> and merge onto <b>N Circular Rd</b>/<b>A406</b>",
              "maneuver": "keep-right",
              "polyline": {
                "points": "omxyHvki@a@jAKXGPCJCLGVET?B?B@H@H@H@P@L@NBPFVDNDJJRJTLPZ`@^d@v@|@`@b@DHVv@hAbATR\\^VZRZRXPXR^R`@LXL^"
              },
              "start_location": {
                "lat": 51.5760845,
                "lng": -0.2170807
              },
              "travel_mode": "DRIVING"
            },
            {
              "distance": {
                "text": "0.4 km",
                "value": 411
              },
              "duration": {
                "text": "1 min",
                "value": 45
              },
              "end_location": {
                "lat": 51.5724353,
                "lng": -0.2274406
              },
              "html_instructions": "Take the <b>M1</b> slip road to <b>Watford</b>",
              "polyline": {
                "points": "i_xyHzjj@LFFBBBBBBDL\\Nf@J\\FTJd@F^H`@Jl@J|@Jz@R`CRrBRbCT`C@NBXBL@L@FBFBLJXFT"
              },
              "start_location": {
                "lat": 51.5738052,
                "lng": -0.2220568
              },
              "travel_mode": "DRIVING"
            },
            {
              "distance": {
                "text": "113 km",
                "value": 113024
              },
              "duration": {
                "text": "1 hour 7 mins",
                "value": 4034
              },
              "end_location": {
                "lat": 52.3245051,
                "lng": -1.1406462
              },
              "html_instructions": "Continue onto <b>M1</b>",
              "polyline": {
                "points": "wvwyHnlk@FJDHJVFPDLFZDTBVBX@V?T?XAXE^?DI\\GVIXMZKX_@dAQd@KRQd@q@hBe@jAg@pA]|@Wn@Qb@Q`@Wl@Q^MTUb@Yj@c@t@k@~@o@bAILEHEPg@r@MPMNYXYXYXKJMJ]\\KHYXQNURg@^w@l@w@h@gAp@a@TWPm@Xo@Zu@\\}@\\{@ZkA^}@Vk@LyAXaBX{@JmAJ_BJ}ABg@@aBC_BGaAEoAIaBOqAOu@Ka@G_AOk@K}@QcAUq@Ou@ScAY{@WqAc@eBm@s@Wi@Se@OcA_@{@YYIgA]u@Qg@Mi@MaASiAQu@Ki@Go@IQASAIAIAq@E}AImBE_A?o@@}@@}@B}@D]B_@B[BSDg@D{@JsBZ}@P}@RiAZC?cAZwBt@wAh@_@Pm@VeB~@wAx@w@d@_An@}AjAs@h@oB`BiBfBkCfCoClCi@h@k@h@cB`B{@x@[ZaA~@_C|B{@x@w@v@cA`AuArAyAvAq@p@q@p@eD`D{CvCwCtCc@b@uDpDSR[Z]ZQRqDlDaE|D{AxAiChCiBdBk@j@}@x@]^uBrBqDlDk@h@w@v@e@b@u@v@aA|@q@p@cAbAsApA_A|@gAfAq@l@_A~@g@d@iAhAyAvAgAdAu@p@o@f@g@`@k@`@MJm@^_@TYPs@^o@Zo@Xm@T_@Ni@Pu@RWHy@Rc@Lu@Na@Jy@LgALq@Hc@FmBVkB\\cATeAZk@Pg@Rk@Vq@\\]P]RWPYPYRWRo@f@[X[Xk@j@i@h@_@b@MPc@h@m@z@e@r@a@p@_@p@Wb@a@x@c@~@g@jAc@hAOb@Sj@Sn@Uv@Uv@Qp@Md@ERIXETGTMn@I`@GZI`@G`@Kj@YrBS~AK|@KjAKrAG~@Ep@E~@E~@CdACf@Ar@AlAAdA?pA@h@@~@BzA@`@BbAJ`CF`ALfBNxAPfBNhAPpARtAN`AVxAb@tCBPHFb@`Dn@lFPvAVpBD^ZtCZtC^fEPpB\\lEHnALjBPxC\\~FD|@Dx@DhABr@BbABbABlA@z@@l@?p@?rAAnBC`BAr@E|ACj@I`BGnAO|BEl@Gp@C\\YjCQdB]nCOlAOfAKr@]xBIj@E\\O`AADIj@Kp@W|A]tBSfAO~@AD_@rB_@rBYxAEPCRk@nC[zAe@tBiA~Eo@jCGXu@tCm@~Bi@pBoBzGk@jBQj@Y|@}@lC_@fAm@fBsAvDo@bBmAbDi@pA_@~@_@|@oBnEs@bBi@pA_@|@c@jAWr@[z@_AxCQf@k@xB]xAOn@[xAYrAm@hD]|BOdAQrAK|@QbBMfAO`BUzBUvBOnAQxAQjAOv@Q`ASdAUfA]vAY`AQl@e@xA[z@Ul@[v@e@`Ai@hAa@r@QZg@x@s@dAe@l@_@d@a@f@a@`@c@b@[XYV_@X[VSLYR[R]R]Rm@X_@P]L]L_AZ_@J}@RcANsARiBP_@FeBP]Dk@F}BVWBi@Fk@Jo@Lc@JSFi@N]LWHuAl@]RSJYR]R]TUNUPo@h@_A~@[ZONe@l@YZORMNc@n@c@r@i@|@]n@Wd@Uf@S`@c@`Ai@jASd@Uh@Yr@aDtHcAdCg@nA_@x@]z@i@nA]z@Uf@Sf@_@z@_@z@ITUd@qA|Cq@`B_@z@eAhCs@dB_@z@]x@e@hAWl@kApCa@`Au@fBYp@Yn@mCnG}@xB_AtBSh@_@z@Sd@IP}AvD}@tB]x@iAlCSd@{@pBWn@]x@_@x@Sh@Ud@i@lAUd@y@|AUb@Wb@o@`Ae@p@W\\Y^UV{@~@]\\WTw@p@]VUPq@b@g@ZSJSJg@Ve@TwD|AmBt@cA`@yAj@sDtAwBx@}@\\mDpA}@\\aA\\q@Vg@Pq@Vm@Ro@Pk@Ns@Po@LC@g@Jg@H_E`@oDN_D?}BE}BQa@G_AMy@IWE_Ba@wB_@}FuAsEy@eBQa@Cg@Ci@CqAGaINkH`AqElA_AZwAj@iAh@s@\\s@`@{@f@u@d@mCfBwFvDeFhDuA~@uAz@sAx@wAx@_CpAgAf@}@b@e@Tw@Zy@\\o@XaBn@eA\\[L[JaA\\mBl@sBl@{Bl@a@J{A^m@La@HyB^_C`@eC`@sDj@oEt@wEp@yBb@}Bf@qCt@mCx@{EzAuBt@gO~E{C`AwAh@k@Rm@TkCx@GBcA\\cA\\kBl@OD}Bt@}FdBaAVmBf@YH_Cn@}A`@aFpA{Ct@WFWFqAZiB`@sBf@{@Ts@PkA\\m@Ry@XaA\\cAb@y@^s@\\gAj@q@`@s@`@w@d@u@h@{@l@m@d@o@h@aAx@gA~@mAjAcAfAeAjAm@p@a@f@}AnBaAtAcCrDyAzB}AdCaAvAiAhBs@jAw@pAy@xAU`@KRc@x@aAlBuApCEFgBhDqA`Cy@xAw@tAy@vA_C~D_BhC}AjC}@zAaA|AuAtByArBsBnC{@bA_AbAmAnAs@r@w@p@iA~@gAx@_An@eAp@_Ah@s@^s@\\s@Zy@\\mAb@q@Tw@T}@ToAXq@Lo@JgANiALaBJgAByABq@?s@AcACs@CeAIsAMqAQiB[eAUc@KcCm@oBa@[G[IOCKCyB_@}AYsAWoAUg@MmB]yCk@gDu@m@KYGIAiASkCg@}Bc@_Cc@iB]sCi@oKsBmDw@uE}@iFcAmGiAkEq@yDa@sHg@iFQmDCsB?wD@}DH]@I@wBJq@D{CPwD`@}ARg@FC?k@HgAJgAPeGj@u@J}H`AaIhAqAN}Dd@iBVmEh@mEh@cD^_Db@aALs@H}Fn@gH`AqFr@q@JqCXWBo@HsDb@cD`@cBReI~@}Fj@UBkFf@wEf@a@BcCTw@FYByDb@{Fd@kBRs@FC@M@i@FoAJwALqGp@eD\\oCVKBgEViAJkBP}Fn@eGj@gFf@wCXeDZcD\\oEd@gE^YDq@Fy@H_AHa@DmE^sD\\}Hn@sNrAsBPaP|AmIx@e@DyC`@_CPo@HcL`Am@FOB]Fs@HiB`@yA\\mA`@kAb@iAd@k@VwAr@iAn@iAr@cBjAeAx@cAz@eA`AsAtAgAnAkAxA}BxCY^Y^mAdBu@dAq@|@uArB_BzBs@`A}@nA}@nAMPo@|@c@l@s@`As@|@yAfBu@z@u@x@q@r@{@v@uAlA{AnAcBtAiBtAuB~AwBdBq@h@q@h@uBbBwAlAiB`BuBlBwCrC_A~@oAnAeBhBkBrBoD`EiBvB}AlBmAzAiB~BgBbCaArAo@|@w@fA{@nAkAfBs@dAe@r@q@fAo@bAo@bAq@fAs@lAq@jAu@nAs@nAm@dAq@lAu@vAs@pAi@dAw@|Aw@|AiA~BiBtDaAtBaAtBw@`Bs@xAq@zAs@~Ag@fA{@lBi@hAi@jA_@z@a@~@k@nA_@x@u@fB}@lBgAhCmAnCg@lA_@z@mAhCi@bAc@x@_@n@u@jAk@t@a@h@a@d@k@l@a@`@k@f@g@^]V[VULMJWN]PQHGDw@\\s@Xe@Ni@N[Hu@Ny@Js@HoALiAHoBPmBNmFh@qBRsARuAZ}Ab@k@Ta@NoAl@oAv@KF}@p@eA|@s@r@o@r@QRc@f@u@`AoBbCw@~@wBfCqA~AkB|BiC~CsCxD}AfBc@d@w@z@wArAMJWTeC|BiA~@}AlAm@`@w@j@{@h@OJOLuCpBkAv@YR{@h@mD`CcEpCmAx@sBtAkCnBoAz@sEzCKFiAt@i@^A?aBhAoBtAiBlAuA`AWPkAx@c@XC@UPm@`@kFnDi@\\wAbAsBtAuBvA_BfAs@d@iEvCgBjA_DvBsDxB}BjAmB~@gDxAwBv@_AZgBh@{A`@oBd@mA\\}AXOBmCd@cC\\mBPeCPgDLwBFyFJyAByAHk@DsCT_@DWBwAR_ANaDh@_B\\wA\\eAXi@Nk@Pc@Lc@NoAb@q@Tm@TSHgBt@gBx@gB|@MHyBlAq@`@_Aj@s@f@cAr@}@n@q@f@m@d@UPm@f@i@b@[XqAhAk@h@a@^i@h@i@h@cAdAa@b@cBlB{@bAk@r@m@r@g@n@A@gAxA]d@k@x@i@t@g@v@w@lAe@t@gAhBcAfBeAlBc@x@a@t@kA~Bc@|@i@hAQZe@bAUd@k@jAUd@_@v@mBtD_@n@aAdBk@`AGLOVU\\Yd@e@r@_@h@iEfGa@j@c@h@c@f@c@h@qAvAk@n@a@^kApAYZURaAbASRc@`@{@v@kAdAaBtA}AjAkA|@iAv@eC~Ag@XyBnAgCpAuB`Au@\\iBt@oBr@oAb@oA^oCt@{A\\kB^}@PcARw@JYDkBVqBTqBPgBJyCHeA@kB@y@?uCGaAAq@Co@AU?k@AyABU?mAF_AFOBaAJoAPgARWDq@LOD}@R_@HkA\\ODu@Vs@XOF{@^c@Tw@^MF[Rk@^YTuA~@sA`Ac@^c@^yAjAgA`AmA~@c@\\]XqB~AeBrAy@p@yBbBkAbAm@f@q@f@MHKHkCtBy@r@[XoB|Aw@p@s@l@w@p@OLiAz@w@l@s@h@a@Zi@b@MLo@f@c@^gH|FiDrCq@j@i@b@k@b@e@^m@f@qDtCgAz@w@n@{AjAWTeF|DoElDgDhCwAfA}@p@s@h@_At@q@h@gA|@{CfCcBvAmAdAcEvDaC~BoApAk@p@[\\[^eBrBaC~CgB~B_@f@eA|AcBhCsAvBQZu@lAy@zAa@t@m@fAk@jAaAjBm@nAm@rA_@t@Uf@g@hAi@jA_@z@]v@{ArDg@tAo@fB]~@[`A[~@qAdE[`A{@xCY~@YbAQn@eAxD[nAWdA_@zA{@xDUdAg@bC[fBSfASdAm@fD]vBU|ASfAQhAWfBm@rDQfA]vBW`BQdAMv@O~@QfAiAjHcCtO_BbK{Gxb@kArHw@`Fy@~EaBpKiAbHq@jEe@rCMv@Mt@]bCy@`FiBjLaAnGG\\Mx@aBhKsBxMIj@G\\u@~EgBjKgE`XoGda@mC`QiDdT_BbKy@lFgF~[]xBk@fDcAlF[|ASfA{@vDYrAa@dB}@zDk@xB[lA_@zAk@pBo@~Bw@fC{CjJsBxFeCdHy@~Bo@dBmAdDiBdFaBrE{BnGsBvFsB|FmAfD{BnGkBdFkAfDcFjNs@pBY~@[|@o@jBk@hBm@jB}@xCi@jBk@nBi@nBW`AW`Ag@pBo@fCeAlEiAdFw@pDuBzJwB|JuC|MuApGcAtEaBxHaAnEoDnP{E|TcAtEm@nCYtA{ApG}AbGw@rCk@nBs@`Cy@hCu@xB_ApCi@fB{@hCiAfDcA`D}BbHYv@kApDeBhFADeCvHoBbGmB~Fk@bB_ApCcBhFqA|De@vAaBrEuCrH_A|BoCpG}BpF{BhFw@jBq@|AKTeBhEaAvBoAzC{AnD_BxDoAtC}AhDoA|CuA`D]v@sGnOwCbHuDtIc@|@]r@aCbFw@bBeDzGy@dBoAjCcArBo@pAWh@Uf@INkBzDa@z@c@z@aDvGCHuCbGw@|Aa@r@Ub@cAjBcA|AaAxAm@z@CDc@h@{@hAaCpCiAfAw@v@sExDk@f@cEjDuIlH}BnB}@t@oB~A_BrAaAx@mAdAgA`AwDpDqBvBgBpBmAvAsBhC}ArBiBfCcClDmDzF}@zAoA|BqCnFoBbEoAnCeDbImCfHcApC}CzHgB~EABYv@[|@e@tA]|@o@dBo@dBw@vBy@xBq@fBg@rA]~@q@fBg@rAg@rA]|@e@rAg@rAg@rAg@rAq@hBq@fBo@fB{@|B{@~Bs@hBo@fByA|DeArCkBbFaCnGuAvDaBnE_CjGmB`F{BnFqA|CmCxFyBnEeC|EuBtD{ExI{Ql\\}NzW{Vdd@sItO_BpCqBrD}@`Bm@dAa@v@aBtCqA|BgAjBeAdBu@hA{A|BcAxASXaArA{ArBW\\w@bAwAdBkAtA]`@_BdBe@j@mDlD{@x@w@t@oE`EgA~@aIfHeA~@eA~@SN}AvAoBdBi@f@_BvAsAlA[Vo@j@kAfAmBfBuDdDu@p@gDxCi@d@w@r@q@l@m@j@[Xo@j@}@v@gA`AoAhAw@r@sAlAgA~@g@d@{BpBeA`Ay@t@]Z{AtAqAnAw@r@KLURuAtAuBrBa@b@iBjB}A`B{@~@mEzEe@h@}AfBaAfAyAfBmAxAy@`AgAtAkAxA_AlAq@z@_@f@wBrCw@bA}@nA{@jA{@hA[d@a@h@[d@w@dAk@z@qAjBo@`A]h@m@~@mAnB{@rAgAdBc@p@k@~@iAlBgAfB_@p@e@v@y@vAo@dAa@t@i@~@]l@cB|CqBrD}DxHcBfDaAlB_CpEaCbFCFsE~JcOh\\m@rAm@tAw]vv@_GrMk@nAkFnLqD~HgB|DyIvRuCnGkAdCeCbF}@dB}AtCA@oBlDmCpEaCbE_BlCaCbEsBlDaBnC_BlCi@`AaBpCcBrCuBpDeAdBu@lAq@lA_FnIyB|DuAlCs@tAyBrEkAjC_AxBiApC}A|DsBtFyBhGs@xBqC|ImAdE}ArFwArFg@rBcB`HqA`GqAlGq@hD_@jBY~AY|AQ~@EVw@|Em@zDgBfMw@fFg@hD]vBe@jCq@vDkAlGq@bDa@jBaBnHCJu@|C{@nDmBdH}@`Ds@|BcAhDwB|GiDlK{EbOaE`MuDdLq@tBk@hBwAtEg@fBqAtEeAzDu@vCk@~B_@zAa@dBYrA_@~Ac@rB]`B[vAI`@s@tDs@tDo@pDq@~Dm@zDYfBq@zEaApHwAnKmBdO}Kh{@mJdt@OhAmAfJkA`JuAnKkBpN_CxQaB`MeAvHa@jCy@rF[pBCNc@rCo@|Dc@dC}@dFShAk@xCs@xDo@`Dg@dCm@vCk@lC[vAu@bD]~Am@jCy@hD{@jD{@fDs@nCk@vBmBfH]pAW|@}@tC_BjFgBzFcDtJ{CtIsAxDeC~GmBrF{BjGuAvDcAtCw@vBoAnDo@hBo@fBg@tAqC|H_AhCoCzHcBzE{BjGmBhFgBvEeAnC}@|BwEbLy@jBo@zAi@lA{FbMk@lAyExJ_HtMuBvD{B~DeCdE{CfF_AxAiBxCkAjB{BhD{BhD{B`DgBfCcBrBiArAeAhAcA`As@p@}@r@u@l@oA`AgAr@}@j@wAt@cAj@u@\\w@\\_A\\kA`@_AX{@VkAXoATmAT{@L}@HmANqADoABmABsDDcAFmBLeAHkAPyAXu@LgAXsBl@y@XeBv@{Ar@eAl@yAz@s@d@g@^q@f@s@l@}AvAwFrFmCdCiFdFkCfCkEfEaA~@i@h@k@f@aF~EeD`DmDbDwFpFeG~F}EvEqDjDaE~DiF`FkDfDuBpBoFlFeB~AeEzDcDvCmDzCgDtCsDxCuErD{BdBgGpEsAv@eBjAoDjCcCdByD|CaClBiCnB_BpAkB~AwEfEeAbAcC`CqDrD{@~@o@r@{@bA}@bAoFfGSVSVi@r@aCvCsD|EqE~FgAxAcFpGgD~DyBjCuBzBqAxAcBlB}A~AmClCaA`A"
              },
              "start_location": {
                "lat": 51.5724353,
                "lng": -0.2274406
              },
              "travel_mode": "DRIVING"
            },
            {
              "distance": {
                "text": "8.8 km",
                "value": 8826
              },
              "duration": {
                "text": "6 mins",
                "value": 388
              },
              "end_location": {
                "lat": 52.4006469,
                "lng": -1.1751908
              },
              "html_instructions": "Keep <b>right</b> at the fork to stay on <b>M1</b>",
              "maneuver": "fork-right",
              "polyline": {
                "points": "esj~H`x}EWTu@r@[ZyBnB{ClCmAfAmAfAyEzDgF|D{CpB{AdAaEfC{EnCeB|@qJtE_DtA}GrCuK~DyGdCsExAuEvAiF|AsA`@eDx@oAVcDr@_ARkF|@uGx@w@J_BH_@D_@B_CPYBWBkGj@cFj@}C^mC^yATsB^kATo@LmB^}Bf@}Bj@wBh@aCp@mBj@qBl@iBl@kBn@yBt@{Bx@wDrA}CfAgDjA{CfAiC|@yCdA{Bv@qC`AcDjAyCbAiC`A{Bv@kC~@iC|@kBp@{Bv@aCx@eC|@gC|@iC|@gC~@}B~@wCnAgBz@yAv@iBbAiBfAkBjAaB`AaB`A{BjAmAj@wBbAkBv@}Al@yCdAyBr@eBd@cCn@}A`@iBd@wA^MDWFUF_Bb@}Bj@uBh@yBj@mBf@gBd@sA^iBb@kCr@uBh@eFrAe@LaAVoIxBiEjA_AV"
              },
              "start_location": {
                "lat": 52.3245051,
                "lng": -1.1406462
              },
              "travel_mode": "DRIVING"
            },
            {
              "distance": {
                "text": "171 km",
                "value": 171207
              },
              "duration": {
                "text": "1 hour 42 mins",
                "value": 6124
              },
              "end_location": {
                "lat": 53.749452,
                "lng": -1.5173591
              },
              "html_instructions": "Keep <b>right</b> to stay on <b>M1</b>",
              "maneuver": "keep-right",
              "polyline": {
                "points": "aoy~H|odF_IfB{J`DoAf@iDtA}@`@}@`@yAp@{EhCkEnCgCtAeAl@iAn@c@ZMHm@^_@Xu@f@q@d@_Ar@{@l@w@l@k@d@g@^k@d@g@`@iA~@aAv@gAbAiB~AiC|Bw@r@i@f@c@Zq@h@gA~@kAz@q@f@mA~@wAbAgAt@gAt@c@Xg@\\aAl@q@`@{A~@kBdA{BlAwAr@yBfAcBx@iChAwAj@yAj@EBoBt@s@VcA\\iA`@aAXwBn@gBf@iBd@eB`@MBgAVA?_AR]FmB`@iBXcC`@eC\\s@FaANsD\\_@DSB{@Fm@DoBJcBHoCJ{@BcABeA@qA?mABcBAaAAq@A_@?eCGgCI}@EI?s@Ei@Em@C_@Cm@GuAKWCe@Em@Eq@Io@GaAMaAM_AMqASq@Io@Mq@MIAe@Io@Ma@I[GYCKAsA[_ASs@So@Q{@Sq@Oy@QeAScAOm@GcAKcAKw@EWC_@Cc@?O?c@Ck@Aq@A_@@o@?y@BcADcAFo@Fs@FcAJq@HaAP[Fy@PwA^w@Ta@L}@Tu@R}@Rc@JK@eARsATu@Jo@JcALeAN_AHsALc@B_AFcAFeADqADcABiA@kA?cAAq@AcACeAEq@EsAIaAGs@GeAIaAGsAMo@EgBMuBOeE]{CMuBGkCCmPQiFGgCCsAAuACaJKq@?eCEuA?gACsAAsAAaACcBAcAAeBCsACs@?wDEW?I?eGIeAAeBCw@Ai@?i@AiAAg@As@A[?q@Ai@?u@AiACo@Am@Ao@A_@Aa@AYAi@Cc@CkAGk@Eq@Ey@Ik@GmAMq@IQCqDg@k@K_@G]Eg@Iw@Km@Kq@KaAOe@G[Gu@Ks@Ke@G_@GUEi@Im@Im@Ii@Ic@IYEWEUE]G_@GWEUE[E_@G]GWCk@Ky@Mu@Ko@Kw@Me@Im@Kq@Mw@Q_@Km@Oi@Oc@Ka@Oc@Mm@U_@M]M]Og@Sa@Oi@W_Ac@y@a@cAi@KE_BaA{AgAgGiEYSq@e@e@]g@]s@g@q@e@o@e@k@a@s@g@y@m@k@_@w@k@k@a@e@[k@a@i@a@g@[]Wk@a@_@Ws@i@m@c@eAu@s@g@q@c@wCmBa@WYQsA}@aBcA{A}@gAs@kAs@cDkBkAq@cDiB]S]SiAk@_Ae@_Ac@_Ac@}@]_A]}Ai@cAY_AYiAW_AUoAU_AO}@OmAOqAMwAKgBIoACmACqA?yA@}@BcADc@@kAJoCTmBVy@NoATeDt@}DlAaDlAgFbCeDdB_@P}GjDsJfF_Bx@kCpAsAp@uBfAcAf@{@b@C@o@ZeBz@wAt@g@Vm@\\i@Vs@^iAl@m@Z}@d@eAf@sAl@cA`@cBn@aBh@{Ab@uAZyAZs@Ls@LkANuANc@De@DcAF}@Fg@@_ADs@?wA?mAAu@Ao@EcBI}BS_AMcBUgBU}AQuAK_BKwBCgC@}ABq@DqAJ_AHmANy@LoARk@Lm@Ng@JqA\\q@Re@PeA^_A\\qCrAkB`AcFtCuBjA{R~Ke@Xe@VaH|DkPhJmNbISLSLkBdAu@b@]PwBlAw@b@yAv@_@P_A`@q@Xa@Pw@XiA^_AXuBh@aARuAVaALg@Hm@Fe@DgAHu@BiABy@Bc@@gA?c@Aq@Aw@C}@EaAG]C_@Eo@G_@Ek@IeAMy@Q_@Io@Om@My@SkFsAcAWmA[}@UiA[sBg@i@O}Cw@eBc@kBc@kDu@y@Mw@MsAS{ASeAKuAOeBMg@COAwAGcCIoBC_DAgDDiDL_AFc@Bc@D{CV]D_@BeBVmBXaBZkB\\qAXeBb@mA\\{Bp@WHYHeC`AWHi@RaBr@}BbAa@R{CzAgBbAeCxAsAz@qChBsCfBuA~@wCpB}@j@iAt@{@j@g@\\mAv@gAr@[R_@Vi@\\{@h@m@`@eAr@uBtAyHbFoChBuBrAwBtAuBrAcC|A}AdAwDbCw@f@_@TgBlAaC~AoD`CgBjAuCnBiC`BcC|Ag@\\o@`@o@b@gLrHqH|Eg@\\OJgIjFk@^u@f@aAv@cAv@k@d@k@f@uAnAgDbDoFrFgInI{@|@yC|CcCdCsDxDuB~B_@b@yA`BmAvAyBpCcAtAeAtAW^Y\\_ArAaChDkBrCmBzCcBpCg@z@gBxC{AnCkCbFoB|Dy@dBMXq@vAkAfCcB|DcBdEmB|E_AfCMXuAxDi@xAi@|A]bAgAdD}@rC}@|Cu@lCo@lC}@hD{@bD{@`DcAfEu@bDy@nDy@vDs@bD_AdEcAnE}AjGsA`FoA|EqA`FeAtDeAvD_A~CcAhDw@dCe@zAEJu@bC_B|EoAnDi@zAc@nA_CnG{AdEgBrEYr@qB`FiAnCa@~@]v@gB~D}AhDoAhCq@tAiBdDk@bAaBlCkAjByAtBkA|AaApAoAzAeAjAq@r@{CzCs@p@o@j@_@\\_@\\mB|Ao@f@o@`@yAbAiBhA{BnAgBbAe@T]PkBx@gBt@mA`@aAXoA^qEhAeCb@kBViCXi@Du@Ds@Dg@Bm@D{@B}@B}@@kCBmCHoAFoAJqAJuANiAPmAPmAT{Cr@wDhAC@w@V{@ZA@kAb@{@ZmA`@w@V}@VaAV}@Ru@Ru@Lu@Nq@Js@J_ALm@HaAJy@HuAHw@D_EJ{@?{AAyAAmAEcV}@gAEmAEsBImAGy@Ce@CsAGuBG_BG}BK{AGaAEmAG_BM{@Kq@KcAOsAWoAYk@O}@W_@Ki@Qm@Sk@Uq@WeAe@q@[u@_@g@Y}AcAaBeAgAy@uAgAkB{AgAeAsAuAiBeB}AwAc@c@g@c@oByAuAcA{AeAkBiAaB}@yAs@iAi@A?eAc@s@Y_Bk@qA_@sBm@_ASkB_@gAQaBU{AOiAI{AI}BIgC?eBBaCHeCPeBJqBFcBBcBBqB?iBEeBGuAKqBQk@G_AM[E]Ga@GQEWCYG}A[sA]y@S}@WwAe@oAc@u@WuAi@eBw@sAo@oBeAkCwA}BiAiEsBoD}AkCcAuCiAwCcAcBk@}Ag@gBg@{@WcAYs@QkCq@aCi@cASaB]eB[cAQgBYwBYiAOeAMmD_@aHk@}@EoDQw@CeAGcACkAAqAE{AEoA?q@?cA?}A@iA@_@@_AFqADu@BiAD{AH}@DuAHaBLYBgAHq@F_@BkDb@o@H}@JcC^MBmBX}B`@cAP{@R_APy@P_ATc@JYFYFe@LmBf@qBj@_Bd@m@Ru@TeBl@sAf@yAh@yAj@mBt@aBp@qBx@mAj@gBx@_CfAs@Zo@\\gAj@y@`@y@b@_Bx@}Ax@sAt@sC~AsBlAg@XOJGBEDs@`@yExCkCdBkAt@gH~EQN_Ap@mDhCyAhASP{AjAqC|BqAdA{ApAiCvBkGvFeGtFmBjBeHhHc@f@i@f@g@j@qLxMqIdKmCfDwBfC{B~BuCrCsDdDuCxBgBlAgC~AmBdAaAh@cBx@eEfByAl@_Bb@]JsEjAYF[Fc@LuB^wBXaAJsBRa@ByBLG@iCFoA?oA?o@?_DGmAGsDWkDc@gCa@}EeAaD_A]MqAa@eBq@sCmA{DaBuQ_IeCeAeDuAyDcBoEkByCoAoJaEqCmAcGgCqDuA}DoA{Bm@i@Mu@SiDs@iB]sBYcBUm@G{@KoAKo@GiAGeAGcAEeBGqCCcBAiBBu@@m@Bo@@u@Bm@Dq@Dw@Fu@Fw@FaAJu@HcANcALeAPcAP_APeAR_B^cARaCp@eDdAiDlAaDpAuB|@oBz@eCbAoClAwGpCqClAwEnB}EpBoBx@a@Na@PuLhFsBz@cGfCeEhBsH`DmBr@wB|@aKfEa@Pc@RwB|@kBv@uB|@yCrA{An@{An@}@^iAf@{Ah@oA^kBf@qAVyARmAN}ANmADoAB}A?oACoAEmAImAMmAQ}@QmAU_AUoA]_A[mAe@}@]m@W[O{@c@iAm@_B_Aa@Wa@YmBuAqBaBeA}@sAqAyB{BaBiBi@k@i@m@g@o@kBwBuAuAqA_BwB_CuBwB{@y@cBwA_CeBeBiA{Ay@eB{@{Ao@}Ao@kBm@oAYaB_@oB]aBO_BMqAIaBE{A?_BDaAD_BJoAL_AL_BZkAR}A`@m@Rk@PqA`@{Ad@aDv@qB`@}Cd@g@Fk@DuCPgABu@AoCKmBKwC[UE{Ca@_AQ]EeBSaBMeAIgBOcBEuBEkBC{BBsB@iBDiADcAFiBNoAFaBJqERo@@_CHiBFC?qBF}BJwCLgBHo@D}AFiDPeELs@@a@AaAA_AGiAGoBYkAS_AUUGoBm@i@OgBs@gAi@c@Sy@e@mAw@e@[e@_@w@m@YU}@w@i@i@WWg@k@s@w@[_@i@o@e@o@_@i@U[{@uAeAgB{@aBe@}@w@cBg@kAu@mBc@mAa@kAUw@i@cB{@sCoByGq@{B_@gAOc@Us@_@cAKWUk@EI[u@q@aBc@_Au@_Bc@y@i@cAa@s@c@s@y@oA]k@c@m@a@i@Y_@_AmAw@}@Y]QSMMkAkAwBmBy@q@yAeA_BcAoAs@k@Y[Oy@a@aA_@q@WmAa@y@WaA[w@Y{Ac@kBo@s@SaA[}Ag@aBi@w@WyDuAiAc@u@]_Aa@i@UeAg@cAi@w@_@UMqDsBgAq@kBoAm@a@YQq@e@EESMcDeCoAeAmAeAgB_BoCmCwAyA[[SWw@{@_AeAeCwC}AoBy@gAmAeBoAeBeA}AgAcB}@wAkAoBaAcBi@_AsAcCkA}Bu@{ASa@eDgHgA_C[s@aByCKOS_@ACS[oB{Ck@w@yAqBiAsAmAsAqAqAmAiAuAkAoA_AqA_AgAs@eAm@cAg@}@e@oAg@mAe@mAa@_Bg@uAa@oA_@]Km@Ue@Qe@Sm@W]QUKm@Y_@Uq@_@e@Ys@c@g@]]U[Uu@k@k@e@}@u@kAiAmAmAq@s@e@i@m@u@[_@CCaA{@i@s@e@o@U_@u@kAoAuBgAsBwAqCuAaDIOmAcDeBwEo@iByAqD_@}@Se@_AsB}AyC}BgE{CwEkCoDiBwBoCoCSUg@c@e@a@mB_BWSIGa@[eBiA{BsAqBeAuAo@c@Sy@_@iC_A_Cu@QGuA]wA]]G{AYkD_@UC_EQoD@_ABc@Bc@BkCTaBV}AXgBd@cAX_@Hk@P_A^mAd@k@Xk@VsAt@s@`@u@f@e@Xo@d@{AhAsAfA_@ZMLGFmBjB}AdB_AjAw@bAo@|@]h@c@n@[d@GJU\\mApBoBxCeBbC}AlBqAvAuAxAURgB|A_BrAeAv@sAz@{BpAm@ZkAj@eAb@aA^{Ad@{@VqBh@oATaAN_BX{Ex@eBX}Dn@cCb@gANwCf@_BXyB\\kCd@_ALiQtCaAN_@HkCb@oCh@oBd@_AT}@T}Ab@aBf@_AX}Bt@g@P[LyBv@}B`A{BdAoAj@uAr@_DfBwDzB_DrBcBfAwAdAeBpASNu@r@w@p@w@l@oAbAsA~@e@Zq@`@o@^}@Zw@`@y@^iAb@gAb@gAZ_AXsAZiARyAPoCZmBNkBFm@Bm@@iFHgADiAFoBPgBTi@Hk@JkAT]HoAZqBl@w@V[JqAj@iAf@w@`@gAl@s@f@k@b@i@`@}@r@aBtAqBlBoApA]`@yAdBABk@r@k@v@i@r@aA|A{AbCkBzCwD|FsBtCqAdBu@|@mAzAaAhAyA~Am@n@}A~A_GnGm@r@u@|@sA~Ae@j@iAxA_ApAcB`CwBbDU`@i@v@i@z@mB~Ca@p@m@hAe@|@m@hA{@bBiCjF}@pBcA~B}@nBcAzBw@hBsAxCiCzFu@`Bw@dB_ApBgBxDkBzDqAdCgCzEwAhCOXOXmDhGkBzC_BhCsB~Co@~@qBvCgAxAcAvAa@l@g@p@oDtEeBvBg@l@qA|AoAvAkArAA@ED}@`Ai@l@}A~Au@v@iAjA_A~@uAvA_B`BaAbA{@z@q@r@y@v@QPq@r@q@p@{@x@}A~Am@l@kCpCgEhEKLo@n@mDnD]\\[Zy@|@]^sArAuA`ByAhBoBvCkAlBe@|@g@~@q@rAq@xA_AzBg@tAWp@M`@e@pAq@~Bs@bCe@nBe@lBa@hB]|A]`Bg@vBg@hBe@bBc@vA}@lCiApCmAhCc@z@o@jAkAfBcAvAkAzAkAnAc@b@}AzAeBlA{@l@}@j@y@`@mAj@yAl@m@RcAZmA^uBx@YLkAh@{@d@}@j@WPaAr@gBzAiAdAoBnBcAfAaAz@_BrAcAt@qA|@_B`AeAj@cBv@{@^y@ZeCx@}A^u@Ni@Jm@LiANuAL{AL}ADcA@iA?gAEa@AiBIw@Ke@CgAOcAQwAYiA[cBg@aA]cA_@eBw@qBgAkBiAuA{@sA{@_BcA{@e@aCiAo@W{Ak@o@SeAYw@Sk@M{@QqAUeAOw@I_AIo@Eq@C{@Cq@Au@?e@?c@@q@@k@B}@Dq@Fi@Dq@JgALm@JeAT_ARWFWF[HoA\\kAXc@HgAXqB^g@JcAPyATiBTqCXqAJ{@FaAFkADk@B{@@q@BiA@{B?q@?mBCaBEqAGeBKa@Ci@EkBQeBSoAOcAO]Gc@GgCg@uBc@qEmA}Ac@mA_@{C_AaD_AqEuAuCy@aEmAyDiAaEoAiA]}OwEuBq@gAUuA[q@OoB_@aAQq@KmAQmAOqAQy@IsBOaAGqBIwAEy@CeBAwB?}A?aCFyBJoCPsCVsAHqAJqCNeJFiBA_CI}AG_BKqAKgAI}@IuAQuASmHmAq@K_BWuASsBUcDW_CQgBIqCImACK?yACwF?kABwBDaEPqBNiCRkBRkBRkAJ}ANkAHs@DQ?s@Bm@B}@@cB@q@?u@?M?[Ac@Aw@Ai@C]C_@AsAIqAKg@Ea@GmDc@q@Ks@MoASk@McASWGwCu@m@QmBg@c@KuAYaCa@uCYc@Ea@E_DQa@Cg@Aw@AeAA_@@q@AsBBiABg@@}BFgDNgBLaBL_@Du@HeCXmC\\{B\\wAXyAXc@Js@N{@Ro@No@Nm@Pq@Pm@Pm@P_AXmA^}@XmA`@mAb@wAj@oElB}@b@wAn@gAj@iAj@iAj@m@\\gAn@_Ah@w@d@iAr@m@^[RgAv@y@h@iAv@{@j@gAt@}@h@{@f@{@f@}@d@iAl@kAj@{Ar@m@X{@^sAh@yAh@}@Z{Af@_Bf@{Ab@mAXyBf@[FqAVqAToC`@aCX_AJoBNmAJaADaBFqADoB@q@?cBAqBCoBE_AC}AE}@CoACuEKoDKgACkBBkAEqBEoAEsAC{@CwAEmBGc@C}@Gm@GUCYEs@Mg@Gs@Oq@QaAYg@Oc@OgAc@c@S_@Oy@c@{@c@y@c@{@g@{@g@{@g@k@]k@_@o@e@qA}@y@k@iA{@w@o@_As@{@s@gB_BaB}AmBkBmAoA{A_BY]k@o@e@i@_@g@_@e@e@i@]c@_AmAs@aAq@aAwAsBaAwAeAaB{@wAgAiBoC}Ea@y@{@_Bm@oA_AoB_AoBaAwBm@uA_@aA]y@_@{@mBoFgBuEeAkC]u@}@mBkA_CmAqBcAcBgA}AsAmBkAsA{@_A{@_Ac@e@m@i@m@g@WWeBuAWQ{AaAqBiA_Ac@}GyCaCeAaCeAqEoBgCiAgCeAkF_CkEmBaEcB}CuA}DgBqD}AgDyAyBaAuCmAwAo@aAa@{B}@[MkAe@wCeAiDiAo@SgEsAgDaA_D{@_FsAoCs@aBe@_D{@cCu@}A_@[Iq@SiA[qEoAkCs@uBo@iAYmBi@yCy@aBc@iBg@yAc@wBq@kEcBmB{@yDiB}BoAsCaByDeCyCwBaCoBwF{EgBsA{@m@{B{AwC_BqB_AyB}@qAc@mCy@q@Og@O[Gw@QyIiB}Be@YImGqAiL}B}Be@}Ba@mBYsAM}BUeAGoBIG?iAEC?OA]AkC?aC@}BHcHd@OBqFp@mAVmAZ_ARsCt@wA`@{Bv@{B|@]PiDzAyBhAkBbAqBrAo@`@eAt@aCfBmBzAq@n@mAdAu@p@yAvAg@h@aCpB[VeBnAiAr@iAn@kAl@kAd@mAf@}Ad@mAZkATiAR}@NqAJeCLqB@oBEmAGeBS}AUi@IuA]aAWsAc@cBq@wAk@iAa@m@YiBu@oBw@y@[_GuBk@Sk@SiEwA}DoAsC{@eCs@aCq@aCo@sCs@oBg@gCk@uCq@_Do@uAY_B[kB_@mEo@oAQ}Gk@cBMeBEmCGgBCeBA_EEg@EmDOiD[gC[mC]OEmH{AgD_AeGgBeC_AmAi@sAk@uB}@yB{@yCeAwC}@aCm@i@MeBc@_Dk@sDm@yAS}Ea@mAEIAsABE?_ABQBgAJc@FaAN}@R}A`@kCv@{Af@{Bx@}@ZeCdAg@TqAj@{Ap@oCvA}A|@YP]T[Ti@`@]Vg@b@]Xi@f@[Zg@h@i@j@YZs@z@g@n@g@p@e@p@o@`AYb@c@r@c@v@c@t@a@z@}@pBk@nAYr@aAdC_@dA[`A]bAUx@]hAW~@_@|ASz@Qv@WhAMr@Kf@[dBSjAG^OdAG`@M~@SbBS|AMnAMxAKjAIrAIhAEr@AZIpACr@Cp@Cf@Ah@Cv@Ar@Cl@Az@Cr@ApAAl@A\\GlFGfDAf@Av@G~CCfCG|DG~CGrEG|DGlDCxBEdCErCApAG|CAlACxACrACjAE|CEnCEtCC|AClBCpBEdCCjBEbCEvCCdBAr@EbBCzBEdDEpGIhHEnFCbECnF@bOLj`@?nA@lAD|L@fE?hD@lBBrK@dFBbDB|@BlAB|@DhBBd@PfEHzAN`CNhBVvCHx@XdCXbCNnAJr@j@nEd@jD^rCNrAPtANlAFh@P|BFv@Ft@L|BBz@Dz@B|A@t@@p@@rA?z@?dAA|@CpAAv@Cv@EjAKlBEr@KjB]vFQxB]zEGh@QzBOjBU`CQlBSnBc@|DG`@Gf@Ip@WbBMn@I`@UnA[vA]vA_@pA_@tAo@pBw@fCw@dC_@jA}AbFm@pBgBvFg@~A[bA]hAqBnGUt@wApEaA`DeAfD}@vC_AxCQ|@a@lAi@tAa@lA_@bAO`@i@tAeAjCq@zAa@|@o@jAm@hAm@fAo@dAe@v@o@~@s@dAe@n@_C|CY^mExFcC|CmGhIaDdE_@f@_@d@kBbCkBbC_@d@a@f@c@j@yAjBs@~@u@~@aAjAmArAs@t@cAnAaBvAiBzA{CbC]V[XkDrCy@r@{@t@YZ[XaA`Ak@l@q@x@i@n@ORWX[b@QPk@|@q@bAYd@e@r@e@t@g@v@u@lAiAdB_AnAu@~@c@j@]`@cAdAu@t@s@n@c@^q@h@yAbAcBfAs@b@o@b@SNeBjAu@f@k@d@s@n@_@^cAhAa@d@q@|@MPOVYd@w@rAQ\\_@t@m@pAw@dBm@vAuGlOiCbG}@tBiAlC{BfFUd@}CfHsCvGuBrEcBdDy@xAsAzB}AhCw@lAu@lAU^cAzAuB|C_@h@cArAc@f@s@|@q@|@k@l@uAtAkElEyCrC{EfEgEjDyB~AaAp@k@\\aB~@mAl@g@TmAh@c@P[Jm@R[J}Ab@]JqAVs@Ls@Jm@J}ANaBJqCFiEDyBDyAJeAFcAHsAR{BXG@eFnAgBh@{Ah@w@Z}@^cBv@YNwBjA_B~@WPIFiBnAuA~@uA`AoAz@kBpA{AdAoA|@eCbBkBnAwEbDyGtEkAx@_HxE}@l@gCdBqBtAgBnAwAbAsB|AiAz@y@n@_Ax@s@l@u@n@i@f@]ZaBzAoBlByB|B_BdB_BfBsC`DkCjCYZo@l@c@`@eA~@aA|@QN}ApAcDdCwAbAyA`AgAr@iAr@{Az@oAr@WL{Av@kAj@{Ap@}@`@MF}Al@gAb@_Bj@sCz@[H]Jk@PcB`@{@VeAZeBj@w@ZmBz@eCnAyA|@wA~@qAbAQLg@b@u@p@WTo@j@y@x@c@b@a@b@_@b@u@z@_AlAs@|@iAbBs@dAo@dAq@jAm@fAyAnCs@xA}@hBuAhCw@xAm@dAaA~AkBlCwAjBaAhAaAfAiAlA[X_Az@gA`A]XURm@b@{AfA{@l@y@l@w@l@k@d@q@f@q@j@k@f@q@p@e@f@c@b@e@h@_@b@i@n@o@z@e@l@a@j@u@`Ay@hAy@fAy@dA}@dAq@r@]\\YVs@n@q@f@o@`@gAp@iAj@m@Vu@Vm@P{@T_ARy@Lo@Fc@Bc@@mA?cACcAIoAQkAWaAWcA]s@Y_Bq@cDyAWKaAa@w@]c@O{@[s@SsA[e@Kq@Iu@IqAKiAC_B?sAFgAHoAPiARoA\\q@Rm@RcAd@aAb@cAj@gAr@w@j@{AlAi@d@}@z@}AxAcA`AuAvAg@f@sAtAkArAw@z@w@~@UXUZw@x@uDxEW\\}AtBkBhCm@x@kAfBcBfCoB`DkAnBu@nAy@tAcAhBuAdCeBxCy@rAaAxAgAxAe@j@m@v@w@|@eAdAs@t@}@x@_Az@i@`@{@n@gDjCcClBeAx@iAz@cBpAcAv@eBtAmG|EqB~AkCrB}@p@oBzAaCjBcBrAwCzBuDvCyBbBiAz@{@p@_Ax@y@r@{@v@k@l@WViAxA_ApAeAbBq@nAWd@c@z@]t@g@lAg@pAo@jBkArDeBtFa@nAk@hBu@bCOVw@`Co@jB[~@{@|B]~@gApCs@dBs@bBk@lAi@lAk@lAw@zAw@~AcAlB{@xAuA~Bm@`Aq@dA}@rAmAbB}@lAg@n@}AhBg@l@cAhAw@x@g@j@eA`Aw@t@gA~@y@p@iAx@k@`@YRKJm@b@eBlAeBdAgB`A}Ax@}@b@{@\\oAh@o@RUJu@Tw@XSD_@Jg@J_ARwAVqBXiCTs@DcCHoAAoAAcAC}AI_CScBUqAQqBg@kBi@_Bk@eBq@aBs@sC{AkBuA[QeBiAqCmBcCaBsBmAq@]e@Uo@Wk@WmAc@kBi@}@So@Mo@Mo@IqAOm@GqAEoAC_B?oADoBPoAPmAToAXmA\\mA`@}@\\m@VkAj@}@b@iAn@k@ZyAz@[Ry@j@y@l@w@n@sAhAi@f@i@f@[Zq@r@g@`@m@r@{@hAa@f@Y`@]b@e@p@[d@c@p@c@t@e@t@i@~@e@v@c@t@i@~@m@bAaA`Bu@pAk@~@e@x@o@~@i@v@q@bA]d@_@f@g@n@i@n@g@l@WZg@j@qAvAWTWVg@b@kB`BiA|@w@l@uA|@yA~@aAj@m@Vk@XgAf@gAf@[LMFi@RsBh@aDv@iAR}AVq@HmBPu@Fe@B_AFgAHi@@gAFaENK?wADqA@_B@gC?wBBcBEkAEaBKaAIaAK}@M}@My@Ou@MyAY}@Wm@Qg@OKE}@YwAg@e@QkAk@}Au@gB_AwA{@gBkAgAu@{@q@w@o@cAy@k@i@eAcAw@w@cAgAu@u@cAgAY]u@y@k@m@q@u@cAmAu@w@cBsBu@y@uA{AqAyAs@q@{@}@gA_AcAy@k@c@c@[c@[OGk@[k@]m@]k@Yo@Wm@U[MmBq@wAa@aC_@_AMq@Ki@Ge@EaAGq@Eq@Cq@AqA?aB?q@@_@Aq@Ao@C_AEo@Io@Im@M}@Um@Qo@Sy@]{@_@y@e@y@g@g@]]Yi@c@i@e@g@e@i@g@u@u@e@e@}AaB}@}@IKaB}A}FwFeCcCqAmAYYyAsAa@_@{@y@USu@q@aBuAwCuBiBgA_BaAiAo@kAm@qAm@uAo@w@[yEeBa@Oa@McCq@i@Oi@Me@Ki@K{@Qs@Mo@Ic@Ga@Cs@Gm@AaAAq@Bg@Ba@Ba@DOB]D[D_@Hg@Jq@Ra@Lq@To@X_Ad@i@Z}@n@u@h@u@l@q@p@q@p@c@d@_@`@[^[^cAlAY^[^_DnDiKrLUV}DvEmD`EoA|AoAxAs@|@iAzAq@`Ao@`A]d@e@v@o@dA{@zAi@bAo@nAa@x@a@z@c@`Ae@dA]|@c@dAq@`Bm@xA{ArDoAjCUb@oAbCq@jAc@t@c@r@c@r@e@r@g@t@kA`Bs@|@}@fAoBtBoBnB_CrBkBxAe@^y@j@cAl@cBbAs@^u@`@g@TiAd@y@\\w@VoA`@qA\\m@Pa@FoB`@yATMBe@Ho@LwHjA{IvAqJ|AsG`AmFz@gEt@gG`AqDl@{Et@cC\\mBPgCNeB@kBCoBEuAIu@GgAKoC_@eAS}@S{@Qk@QqBm@s@U]M_@Oa@QcCgAsBeA{BmA{BqAmDsB}CqBgDeCkE}CkCuBs@o@y@u@}@_AaA_Ao@s@cCsCq@_Ae@m@i@w@{A}Be@y@iAmBk@cAi@gAg@aAa@{@_@w@_AsBk@sAg@sA}@cCa@iAg@{AK_@[cAq@}BSq@Uy@Uy@{AkGw@aDk@sBq@gCm@aC_@mAe@yAg@uAo@cBq@gBq@cBq@_Bo@wAaByDaA}BuAeDqAuC{DkJi@oAyAkDwAgDaA}B}@uB}@yBaFgL}AsD_AyB_A{Bq@_Bs@aB[s@[q@Wi@IOIQm@mAo@kA]m@eAcBa@o@mAeBe@k@w@aAq@u@g@m@q@q@k@i@c@a@yAoAsA_AqCeBcBy@yAo@{@]mAa@}@WqDaAs@MiDYeC@gC?[@c@@w@FcAJkANuATiCn@kA\\w@XoAf@oDdBQJs@\\s@\\c@TsCxAcDbB{BfA{Av@iAj@gCrAyBfAeB|@qCvAgAd@qBn@_@HgATgAPC@mBPS?gABcA?eBGeAO"
              },
              "start_location": {
                "lat": 52.4006469,
                "lng": -1.1751908
              },
              "travel_mode": "DRIVING"
            },
            {
              "distance": {
                "text": "5.3 km",
                "value": 5265
              },
              "duration": {
                "text": "4 mins",
                "value": 215
              },
              "end_location": {
                "lat": 53.7832722,
                "lng": -1.5427233
              },
              "html_instructions": "Keep <b>right</b> at the fork to continue on <b>M621</b>, follow signs for <b>Leeds (Centre)</b>",
              "maneuver": "fork-right",
              "polyline": {
                "points": "a}`gInjgHQCu@OaB_@i@Qk@UeAa@sAq@gBcAaBcAkAu@aBaAkB_AaBq@]M}@YeAWSE_AMMCYCy@Gg@Eq@Au@?{@?mBBg@@kB?o@?Q@_A@uBDSAwAIk@GaAGmBKOA}@EgAEuAEWAgA?oBA[@U?[?[?_@@_@?k@@k@@g@@k@Bw@D{@F_@Da@F}@Nk@Pc@Nm@Xe@Vw@h@e@b@YXONIHMP[^QTQZMNQ\\_@r@_@x@Sd@Wt@Sj@Qj@Oh@Kb@Ib@IXKl@I^OfAOfAIr@Iv@MrAIdAIpACf@GtAAZChAC`AAt@?pA?t@?~@?TB`FA|AAVEvBSzDE|@MlCEhA?\\A\\?\\A|@@zB?P@|C?Z@l@@xBDdI@dC@hBAjAAhA?XCn@Cz@C\\W`CSpAMn@On@Mb@Qn@M^Qb@O^OZUd@Ub@UZOTQRWXk@f@m@d@QJ_@PWJ[JUFYFUBYBk@@U@QAs@Ia@G{@Ys@_@{@i@y@m@w@m@wAiAw@o@c@]o@e@c@[[Sa@Sc@Qa@M_@IWCa@CM?[@_ADc@JUHE@WJEB]ROHMHOJ]Ty@l@o@d@eBpAmCrBYVq@l@]\\ORc@l@QTU`@U`@KRKRUh@GTSd@Wv@M\\o@pB"
              },
              "start_location": {
                "lat": 53.749452,
                "lng": -1.5173591
              },
              "travel_mode": "DRIVING"
            },
            {
              "distance": {
                "text": "0.3 km",
                "value": 338
              },
              "duration": {
                "text": "1 min",
                "value": 29
              },
              "end_location": {
                "lat": 53.7831593,
                "lng": -1.5432495
              },
              "html_instructions": "At junction <b>3</b>, exit towards <b>Central Leeds</b>/<b>Holbeck</b>",
              "maneuver": "ramp-left",
              "polyline": {
                "points": "mpggI~hlHKt@WhAQ~@Gd@Ef@AJ?JAL@J?J@J@JBNBHBJDHBFDDFHBBHFHDD@H?D@HAFADCFCFEBCHI@EDIFOBMDQ@Q@O?Q?MAKASESEQEKQ_@Wi@MY"
              },
              "start_location": {
                "lat": 53.7832722,
                "lng": -1.5427233
              },
              "travel_mode": "DRIVING"
            },
            {
              "distance": {
                "text": "0.3 km",
                "value": 257
              },
              "duration": {
                "text": "1 min",
                "value": 25
              },
              "end_location": {
                "lat": 53.7848108,
                "lng": -1.54448
              },
              "html_instructions": "Merge onto <b>Dewsbury Rd</b>/<b>A653</b>",
              "maneuver": "merge",
              "polyline": {
                "points": "woggIhllHMMi@o@k@o@OEQBGBIHGFENIRQ~@[bBQr@K`@EJIJGBMHa@HE@"
              },
              "start_location": {
                "lat": 53.7831593,
                "lng": -1.5432495
              },
              "travel_mode": "DRIVING"
            },
            {
              "distance": {
                "text": "0.4 km",
                "value": 361
              },
              "duration": {
                "text": "1 min",
                "value": 39
              },
              "end_location": {
                "lat": 53.7865837,
                "lng": -1.5480252
              },
              "html_instructions": "Continue straight onto <b>A653</b>",
              "maneuver": "straight",
              "polyline": {
                "points": "azggI~slHQDODGDE@ONMRKVGRGTCVAXAZ?^JpA@\\@^?XA\\Gj@G^IXIXIPGPINOTOPSPOJWLOBSD}@B"
              },
              "start_location": {
                "lat": 53.7848108,
                "lng": -1.54448
              },
              "travel_mode": "DRIVING"
            },
            {
              "distance": {
                "text": "0.2 km",
                "value": 204
              },
              "duration": {
                "text": "1 min",
                "value": 25
              },
              "end_location": {
                "lat": 53.7881067,
                "lng": -1.5465183
              },
              "html_instructions": "Slight <b>right</b> onto <b>Meadow Rd</b>/<b>A653</b>",
              "maneuver": "turn-slight-right",
              "polyline": {
                "points": "cehgIdjmH_B_ASMw@c@AAWMYS]WIKGKGQK]Mw@"
              },
              "start_location": {
                "lat": 53.7865837,
                "lng": -1.5480252
              },
              "travel_mode": "DRIVING"
            },
            {
              "distance": {
                "text": "0.4 km",
                "value": 429
              },
              "duration": {
                "text": "1 min",
                "value": 48
              },
              "end_location": {
                "lat": 53.7914351,
                "lng": -1.5472604
              },
              "html_instructions": "Slight <b>left</b> to stay on <b>Meadow Rd</b>/<b>A653</b><div style=\"font-size:0.9em\">Continue to follow A653</div>",
              "maneuver": "turn-slight-left",
              "polyline": {
                "points": "unhgIv`mHMYMc@EMGKGKGKIEIEKGICMCOCMAM?S?K@?@IBGBEDIFa@`@GJGNCHELMd@Qh@Sf@W`@KJGHOJOHUFMBK?M@{@CSA]CUEWEc@G"
              },
              "start_location": {
                "lat": 53.7881067,
                "lng": -1.5465183
              },
              "travel_mode": "DRIVING"
            },
            {
              "distance": {
                "text": "0.1 km",
                "value": 103
              },
              "duration": {
                "text": "1 min",
                "value": 18
              },
              "end_location": {
                "lat": 53.7923493,
                "lng": -1.5470646
              },
              "html_instructions": "Slight <b>left</b> onto <b>Victoria Rd</b>",
              "maneuver": "turn-slight-left",
              "polyline": {
                "points": "ocigIjemHEBG@E?OA_@G_@E_@IKIOCIAKC"
              },
              "start_location": {
                "lat": 53.7914351,
                "lng": -1.5472604
              },
              "travel_mode": "DRIVING"
            },
            {
              "distance": {
                "text": "0.3 km",
                "value": 326
              },
              "duration": {
                "text": "1 min",
                "value": 54
              },
              "end_location": {
                "lat": 53.79525899999999,
                "lng": -1.5464209
              },
              "html_instructions": "Continue onto <b>Neville St</b>/<b>Victoria Bridge</b><div style=\"font-size:0.9em\">Continue to follow Neville St</div>",
              "polyline": {
                "points": "eiigIbdmHE?eBSe@Gw@KkC[c@GWEWEo@Kq@IA?ECEAAAA?WEOC"
              },
              "start_location": {
                "lat": 53.7923493,
                "lng": -1.5470646
              },
              "travel_mode": "DRIVING"
            },
            {
              "distance": {
                "text": "0.2 km",
                "value": 168
              },
              "duration": {
                "text": "1 min",
                "value": 46
              },
              "end_location": {
                "lat": 53.7961702,
                "lng": -1.5480135
              },
              "html_instructions": "Turn <b>left</b> onto <b>Bishopgate St</b>",
              "maneuver": "turn-left",
              "polyline": {
                "points": "k{igIb`mHKPIHUT]VSLQFe@HKJCFA@AFADAR?PAJ?PEjB"
              },
              "start_location": {
                "lat": 53.79525899999999,
                "lng": -1.5464209
              },
              "travel_mode": "DRIVING"
            },
            {
              "distance": {
                "text": "0.2 km",
                "value": 192
              },
              "duration": {
                "text": "1 min",
                "value": 34
              },
              "end_location": {
                "lat": 53.7973661,
                "lng": -1.550117
              },
              "html_instructions": "Turn <b>right</b> onto <b>Quebec St</b>",
              "maneuver": "turn-right",
              "polyline": {
                "points": "aajgI`jmH[v@c@h@eAbCUd@sAxC"
              },
              "start_location": {
                "lat": 53.7961702,
                "lng": -1.5480135
              },
              "travel_mode": "DRIVING"
            },
            {
              "distance": {
                "text": "54 m",
                "value": 54
              },
              "duration": {
                "text": "1 min",
                "value": 12
              },
              "end_location": {
                "lat": 53.7977494,
                "lng": -1.5496104
              },
              "html_instructions": "Turn <b>right</b> onto <b>King St</b>",
              "maneuver": "turn-right",
              "polyline": {
                "points": "qhjgIfwmHUWS_@[g@EE"
              },
              "start_location": {
                "lat": 53.7973661,
                "lng": -1.550117
              },
              "travel_mode": "DRIVING"
            },
            {
              "distance": {
                "text": "0.2 km",
                "value": 206
              },
              "duration": {
                "text": "1 min",
                "value": 39
              },
              "end_location": {
                "lat": 53.7995622,
                "lng": -1.5491082
              },
              "html_instructions": "Continue onto <b>E Parade</b>",
              "polyline": {
                "points": "}jjgI`tmHECGGEAKE]IeA]}@UkAQ{A?"
              },
              "start_location": {
                "lat": 53.7977494,
                "lng": -1.5496104
              },
              "travel_mode": "DRIVING"
            },
            {
              "distance": {
                "text": "0.1 km",
                "value": 132
              },
              "duration": {
                "text": "1 min",
                "value": 26
              },
              "end_location": {
                "lat": 53.8007507,
                "lng": -1.5491248
              },
              "html_instructions": "Continue onto <b>Calverley St</b>",
              "polyline": {
                "points": "gvjgI|pmHS?[?gCDu@C"
              },
              "start_location": {
                "lat": 53.7995622,
                "lng": -1.5491082
              },
              "travel_mode": "DRIVING"
            },
            {
              "distance": {
                "text": "0.3 km",
                "value": 275
              },
              "duration": {
                "text": "1 min",
                "value": 70
              },
              "end_location": {
                "lat": 53.8008726,
                "lng": -1.5449591
              },
              "html_instructions": "Turn <b>right</b> onto <b>Great George St</b>",
              "maneuver": "turn-right",
              "polyline": {
                "points": "u}jgI~pmHA{@C_AIcFSsGAg@LcD"
              },
              "start_location": {
                "lat": 53.8007507,
                "lng": -1.5491248
              },
              "travel_mode": "DRIVING"
            },
            {
              "distance": {
                "text": "0.3 km",
                "value": 297
              },
              "duration": {
                "text": "1 min",
                "value": 63
              },
              "end_location": {
                "lat": 53.8006785,
                "lng": -1.5405898
              },
              "html_instructions": "Continue onto <b>Merrion St</b>",
              "polyline": {
                "points": "m~jgI~vlHBe@Bk@Bw@@[?CBgA@m@Bm@@W`@cIFu@D_AEKISSi@"
              },
              "start_location": {
                "lat": 53.8008726,
                "lng": -1.5449591
              },
              "travel_mode": "DRIVING"
            },
            {
              "distance": {
                "text": "0.2 km",
                "value": 167
              },
              "duration": {
                "text": "1 min",
                "value": 22
              },
              "end_location": {
                "lat": 53.8021409,
                "lng": -1.5404209
              },
              "html_instructions": "Take the <b>Inner Ring Road</b>/<b>A58(M)</b> slip road",
              "polyline": {
                "points": "g}jgIt{kHQMSQGEGEICGAM?y@DiBNE?E?]E"
              },
              "start_location": {
                "lat": 53.8006785,
                "lng": -1.5405898
              },
              "travel_mode": "DRIVING"
            },
            {
              "distance": {
                "text": "0.5 km",
                "value": 486
              },
              "duration": {
                "text": "1 min",
                "value": 29
              },
              "end_location": {
                "lat": 53.8051196,
                "lng": -1.5448793
              },
              "html_instructions": "Merge onto <b>A64(M)</b>",
              "maneuver": "merge",
              "polyline": {
                "points": "kfkgIrzkHMBy@NA?c@Fy@Pe@L[L_@R[TOLMLc@b@MTYb@a@r@Yr@O^GRQn@Qp@WtAQxAMfAIbAIrA"
              },
              "start_location": {
                "lat": 53.8021409,
                "lng": -1.5404209
              },
              "travel_mode": "DRIVING"
            },
            {
              "distance": {
                "text": "1.7 km",
                "value": 1675
              },
              "duration": {
                "text": "2 mins",
                "value": 99
              },
              "end_location": {
                "lat": 53.7961624,
                "lng": -1.5625001
              },
              "html_instructions": "Continue onto <b>A58(M)</b>",
              "polyline": {
                "points": "_ykgInvlHE~@CbAC`A@BA|@@xB@z@DbBDn@HtAHz@LnAFf@Hp@Lr@Jp@Lr@Ll@Nl@Lb@Ld@Pl@f@vA|@~B`@x@BHJLz@nAZb@RXTR\\`@^ZhAt@lB~@ZJLDb@J^HPBTD~ARv@JTB`@Jf@R\\P\\VTVRVPTT`@HTP`@FPL`@T~@DVDVHf@Fd@Jt@N|AJv@F^D`@H`@F^H^HVBLLf@Rj@J\\LZLZLXLZNVNXNXLV^p@t@vAt@xAr@vA"
              },
              "start_location": {
                "lat": 53.8051196,
                "lng": -1.5448793
              },
              "travel_mode": "DRIVING"
            },
            {
              "distance": {
                "text": "0.4 km",
                "value": 388
              },
              "duration": {
                "text": "1 min",
                "value": 34
              },
              "end_location": {
                "lat": 53.7934095,
                "lng": -1.5658037
              },
              "html_instructions": "Continue onto <b>Wellington Rd</b>/<b>A58</b>",
              "polyline": {
                "points": "_ajgIrdpHb@|@z@bBjAdCf@dAP^R^NZP^PZHPNPJJNLHFXRRLD@LHZHD?TD|@H"
              },
              "start_location": {
                "lat": 53.7961624,
                "lng": -1.5625001
              },
              "travel_mode": "DRIVING"
            },
            {
              "distance": {
                "text": "1.5 km",
                "value": 1479
              },
              "duration": {
                "text": "2 mins",
                "value": 100
              },
              "end_location": {
                "lat": 53.7807133,
                "lng": -1.5679593
              },
              "html_instructions": "At the roundabout, take the <b>1st</b> exit onto <b>A58</b>/<b>A643</b><div style=\"font-size:0.9em\">Continue to follow A643</div>",
              "maneuver": "roundabout-left",
              "polyline": {
                "points": "yoigIfypHPAP@NBPDNHNJNLLNPHRTPXTXPNPJXLr@ZD@l@P^Jn@Ll@H^Db@F@?b@B`@@ZAP?z@I^GPEvBi@zA]d@KhASr@INAhAKhAGP?F?`@@PBLBVJRHJDRNZZb@h@d@n@d@r@^d@h@l@d@`@XLLDt@Tb@HT@|@H~DRR?f@Al@A|AOpAO\\KLGFEDGHMXg@"
              },
              "start_location": {
                "lat": 53.7934095,
                "lng": -1.5658037
              },
              "travel_mode": "DRIVING"
            },
            {
              "distance": {
                "text": "0.5 km",
                "value": 483
              },
              "duration": {
                "text": "1 min",
                "value": 48
              },
              "end_location": {
                "lat": 53.7796533,
                "lng": -1.5724136
              },
              "html_instructions": "At <b>Elland Rd Interchange</b>, take the <b>3rd</b> exit onto the <b>M621</b> slip road to <b>Manchester</b>/<b>Halifax</b>/<b>Huddersfield</b>/<b>M62</b>",
              "maneuver": "roundabout-left",
              "polyline": {
                "points": "m`ggIvfqH@QBMFSDMHWRMLIPGPC~@@RFHDPJJNHPJRHd@BP@d@?XAXG`@?@ETEJCFGJId@ETEXCXCZC\\A\\?j@?^?f@?p@@h@@h@@f@@d@Bd@HjA?JAj@"
              },
              "start_location": {
                "lat": 53.7807133,
                "lng": -1.5679593
              },
              "travel_mode": "DRIVING"
            },
            {
              "distance": {
                "text": "7.0 km",
                "value": 6994
              },
              "duration": {
                "text": "4 mins",
                "value": 265
              },
              "end_location": {
                "lat": 53.7459071,
                "lng": -1.6517009
              },
              "html_instructions": "Merge onto <b>M621</b>",
              "maneuver": "merge",
              "polyline": {
                "points": "yyfgIpbrH@LHt@Jr@Hn@@JJh@Jp@X|ATfAVfANp@X`APl@ZbA\\dAFPLR`@|@~@tBJT~A~CdAlB|@`Bt@zA\\r@t@|Ax@fBt@bBzDdJzBfF~CnHr@`BRd@b@~@v@|Ah@~@j@~@`@l@~ArBPPl@l@l@p@dDhDfElEPRPRlBlBhIvI`BdB~BdCbAfA`CrC~AvBz@lApAxBn@dAfArB~@lBr@xAlBlErAfEjAlD~@tCnA|DjApDn@zBr@~BnAtDtAxDnA|ChAjCnAhCj@dAtAbCrAxBvAnBjBbCtA`BhAnAt@r@z@|@t@t@lAlAx@x@jBhBtBtBdCbClBjBvBxBDFrAtAFJfBrBTZp@dAx@vAb@z@NXDH^v@Tf@Rf@JV\\`AZ|@Pj@ZdAXbANl@T`ANp@\\lALl@Z`BPdATxA^hCNnANbBLjBB^Dx@B`@@VDdA@jA?\\?t@?v@A\\Ap@Ab@Cl@Ep@C\\Ir@I|@CJU~AWxAKj@Kj@Or@Mt@SfAYzAUnAUjASdA[bBSjAOjAOjACZMlAGt@Ev@Ep@EdAAHA\\ChBArA?t@?lA@\\?X@ZBv@HhBFjAHtAVrDPdCVbE^nFNxBNxBr@xIT|C@Z@l@@|@"
              },
              "start_location": {
                "lat": 53.7796533,
                "lng": -1.5724136
              },
              "travel_mode": "DRIVING"
            },
            {
              "distance": {
                "text": "37.4 km",
                "value": 37384
              },
              "duration": {
                "text": "23 mins",
                "value": 1359
              },
              "end_location": {
                "lat": 53.6046552,
                "lng": -2.103306
              },
              "html_instructions": "Merge onto <b>M62</b>",
              "maneuver": "merge",
              "polyline": {
                "points": "}f`gIbraIVpCPjBJfATlCp@~G~@pKh@|Fd@zF^hEFt@d@tFFj@z@rJdBrRJjA|@lKVhCFr@Fr@D`@`@|Ef@|ETnCVvC~@hKPpBz@~J^bFFnADlAFdADzAD`BDzBBtB@xDCnDE~CI`DMpC[|F[jD[bDShBc@`Da@nCa@zBm@zCo@rCw@`D{AlFyCbKiArEq@zCk@zC[rBUlBYpCWtCM`BMjCA\\Cf@G`BAhACzA?`A?bB?`ABjAFjCHxBLfCPbCRvBLlATbBL~@Jr@XbB`@rBRfAZnANn@Pr@Tr@^lA\\dAXt@b@hAn@tAb@~@`@v@Xh@T`@b@t@@@p@dAhA|At@bAz@fAx@bA`AjAvBjChCxC@@LJnAxApAvAxB~Bj@j@^^@B\\ZpArAnCjCjBjB`@^BB\\Z|AvAhA`ArAlAzCfC@@DBfEhDvB`Bx@l@nCnB|@l@fAv@lAz@r@f@v@h@^T`DlCfA`A|BzB|@|@n@p@dAlAl@p@`@d@Z`@b@f@h@p@X\\p@|@VZf@p@~@rABDV^PV@BX`@b@p@Xb@RZ\\h@`@p@Zh@Zh@\\l@b@t@b@x@^n@l@fAd@t@\\f@d@r@f@r@h@n@v@`Aj@n@v@v@t@t@r@n@x@n@x@l@r@d@~@j@|@b@DB~@b@dA`@XJ\\Lj@P\\J\\Hf@L|@PzARv@Fx@Hp@Br@@n@?hAA^A^AhAKdAKj@I`Ca@r@ObB]pAUxAYxAY`B[h@KdASvAYv@Q|Ci@lAUd@KpFaAh@Kn@Mj@Kn@I`@Ex@EZAvA?h@@v@DvANdARfAXx@Vj@Tb@Rx@`@j@\\l@^x@n@h@b@h@f@b@b@h@j@TXVZd@n@RVx@rAx@xATb@P\\^v@b@bAv@lBRl@\\|@t@nB`@hAvA|DnAhDbAhC^|@@D\\t@hA~B`A~ANTX^BD\\f@rA~Af@f@ZX^^l@b@pAjAl@h@n@h@v@p@^\\t@l@bA|@dA~@~AtAnDxCvClCn@l@l@n@JLp@x@j@v@p@bAh@|@\\l@`@x@d@dAZr@n@zAL`@Rl@`@jA\\rAVz@Rv@VhARfAThAN|@F`@Hf@VrBRlBZjDj@jGb@jFh@bGPtBXdDTvCXxCRdCRxBZrDt@vI^hEV~CFl@R|B^bEn@rH`@`Fr@`IPtBdAzLb@hFn@jHv@hJN`BL~A|@dKTvCVnCXdDNhBT`Ct@~I\\vDRzBJfAHdAZlD\\pEZ`Ef@tFZ`DPvAPpA`@jCP~@\\`BPt@h@vB^rA`@rAd@nAr@jBf@jAv@fBXj@hAdCbA~Bl@xAl@jBd@~A`@zAVbAl@pC^zB\\~B^vCz@fIdCvUFl@@BP~APdBX~B\\|CZtBb@pCZ|A`@nBf@tBJ`@HV?BFPNl@d@~ARn@lAjDf@nA~AxDfBdErD~I`@~@j@rArDxI~AzDXp@JXXl@Vn@`@dAd@jAt@pBr@lBv@tBHXJVzBbH~AlFjBxGjBpHd@nB`AhE~AtHtD~PBJhA`FbAvEl@zBl@zB\\pATdA\\lA^~At@vCp@`CbAjDp@fCfCvInB~Gj@pBb@~ARl@r@bCt@hCp@|B`AfDxBtHX`AFPPp@|@~C`AdDXbAr@bCf@hB\\fA^lAp@tB\\dA`@jAl@dBh@vAh@tAl@xAp@`Bv@dBp@|AvBfEf@x@z@`Bl@hA~EhIr@lAzDxGp@jAd@|@|@~AjAtC`BnEn@jC^zAf@pC`@tBVhBThBLrAR`CNvCHzBB~BBrCAxBAjAInCMxCSzC_@pGYjEYdDSdD_@pGK~AIz@ARMpBG|@IjAGv@Er@SjCCn@c@rGgAxPQvBOrCIrAQxCM`COnBU|CQhCOpB]bFi@~HYbFEx@EjAEvAIlBEpCAxBAjB?fBB~DLvHj@~LfAdMt@bGRvA\\zBRhAXxA^nB^~ALn@l@fCdAtDd@|Ar@vBpBxFnBlEfA`Cp@~A`AdCj@`BfAjDp@bCh@zBp@`Df@pCZjB^nCTjBZtCXdDPdDRpDLbDz@bR@Lh@lKh@dLl@|MTrDZ`EV`DPlBhBzM|DtUzAdJn@tDvAlJhBnLbBjLZzBf@rD~BxPjAjJFj@`AzHRhBt@xGzAfNjB~QnA~Mp@dH^rEr@rITdD\\hEd@nHL|ANnCN~BVxEHpA\\tG^bIThFHpCHrC\\pORxJ@|@FtC@~@BjA@lAJzJ@`BFlN?nF@`BBnEFvCLfCNrBJbAFx@Jx@NjA\\rBDTh@bC`@`Bf@dBt@`CX|@^jAzAlE|@nCl@jBFNl@tBl@hCn@`Dd@fC^jC`@bDVhCBZNfBLbBLrBLzC@b@LrEDnBPpKJ|KDpJArE@vFCpIIfLAf@KnKMrHMxG?bAAvA@jA@hABjAD`ABt@Dt@Fp@H~@Jv@Jz@Z|BRhAXxAZpAXhAXbATx@\\bA^dA`@`A`@~@`@`Aj@nAv@jBx@lBjAjC^|@BB\\v@hBfEjB`Eh@hAj@dAj@~@x@rAT\\n@z@n@v@t@t@r@t@dAz@x@r@t@p@f@^j@\\^Rt@`@l@Td@Pr@Xn@R|@X~@Xz@Zl@Tn@Tl@Zp@Zx@d@l@Zj@ZNLZR\\T\\Th@b@\\Vx@r@t@t@fAhAd@h@t@|@~@nAr@`A^h@j@z@fAfBx@zA|@bBp@rAj@rAr@dBt@pBt@pBb@vAl@nBp@xBbBlF^pA|@tCJ\\hAjDbBpF"
              },
              "start_location": {
                "lat": 53.7459071,
                "lng": -1.6517009
              },
              "travel_mode": "DRIVING"
            },
            {
              "distance": {
                "text": "0.9 km",
                "value": 944
              },
              "duration": {
                "text": "1 min",
                "value": 51
              },
              "end_location": {
                "lat": 53.6016208,
                "lng": -2.112842
              },
              "html_instructions": "At junction <b>21</b>, exit towards <b>Milnrow</b>/<b>Shaw</b>/<b>A640</b>",
              "maneuver": "ramp-left",
              "polyline": {
                "points": "ctdfItxyKXRBFDJJVFP@BRn@P`@Rf@N^JZtAjDXn@N\\P\\JPVf@h@p@f@n@h@d@h@`@j@\\f@Zf@XbAp@j@d@VVRVb@t@Rf@Nd@Jf@Lt@FdA@b@?b@?`@Ad@I`AIl@Kf@St@O`@GPGFCHOT]b@GFEDSNKHKFKFEBOFMHKNQh@"
              },
              "start_location": {
                "lat": 53.6046552,
                "lng": -2.103306
              },
              "travel_mode": "DRIVING"
            },
            {
              "distance": {
                "text": "0.2 km",
                "value": 186
              },
              "duration": {
                "text": "1 min",
                "value": 16
              },
              "end_location": {
                "lat": 53.6010451,
                "lng": -2.1154568
              },
              "html_instructions": "At the roundabout, take the <b>1st</b> exit onto <b>A6193</b>",
              "maneuver": "roundabout-left",
              "polyline": {
                "points": "cadfIft{K?D?B?B?DAB?BAD?BF`@Jt@TzANbAz@lF"
              },
              "start_location": {
                "lat": 53.6016208,
                "lng": -2.112842
              },
              "travel_mode": "DRIVING"
            },
            {
              "distance": {
                "text": "1.4 km",
                "value": 1383
              },
              "duration": {
                "text": "2 mins",
                "value": 105
              },
              "end_location": {
                "lat": 53.6063398,
                "lng": -2.1325519
              },
              "html_instructions": "At the roundabout, take the <b>1st</b> exit onto <b>Sir Isaac Newton Way</b>/<b>A6193</b><div style=\"font-size:0.9em\">Continue to follow A6193</div><div style=\"font-size:0.9em\">Go through 2 roundabouts</div>",
              "maneuver": "roundabout-left",
              "polyline": {
                "points": "q}cfIrd|KHFHHHPFRBP?VATCLCLENEHCBGDCBMFSlBEf@Cd@AREp@EbA?DCfACfA?x@?J@rA@nA?hACpAErB?LGtAI`BCj@C^Gh@@D@@?B@@?B?B?@@B?B?B?@AB?B?@?BAB?@A@A@A@?@A@A@A@A?A@A?A?A@A?AAKRKZMPCJkDnJqEzL@@@@?@@@?B@@?@@@?B?@@B?@?@?B?@?B?@?B?@AB?@?BA@?@AB?@A@?@A@A@?@A?A@A@A@A?A?A?A?A?A?A?AAA?AAA??AAAAAAAi@pA}@nBoA~BkCbFm@nAw@lB]fAEN?PCRGR"
              },
              "start_location": {
                "lat": 53.6010451,
                "lng": -2.1154568
              },
              "travel_mode": "DRIVING"
            },
            {
              "distance": {
                "text": "0.3 km",
                "value": 259
              },
              "duration": {
                "text": "1 min",
                "value": 47
              },
              "end_location": {
                "lat": 53.6070852,
                "lng": -2.1360597
              },
              "html_instructions": "At the roundabout, take the <b>1st</b> exit and stay on <b>A6193</b>",
              "maneuver": "roundabout-left",
              "polyline": {
                "points": "s~dfIlo_LBB@B@@@B@D@B@B?D@B?D?B?D?D?B?DAB?DABADABABABA@ABC@A@A@M^Ib@Gn@Cx@Gn@Gv@O|@Mv@Mp@U|@YnA"
              },
              "start_location": {
                "lat": 53.6063398,
                "lng": -2.1325519
              },
              "travel_mode": "DRIVING"
            },
            {
              "distance": {
                "text": "0.3 km",
                "value": 282
              },
              "duration": {
                "text": "1 min",
                "value": 50
              },
              "end_location": {
                "lat": 53.6091241,
                "lng": -2.1381504
              },
              "html_instructions": "Continue straight onto <b>Moss Bridge Rd</b>",
              "maneuver": "straight",
              "polyline": {
                "points": "icefIje`LO`@O^A@EFgBdFy@j@_@TWL[JKBI@MBI@iAF"
              },
              "start_location": {
                "lat": 53.6070852,
                "lng": -2.1360597
              },
              "travel_mode": "DRIVING"
            },
            {
              "distance": {
                "text": "0.6 km",
                "value": 650
              },
              "duration": {
                "text": "2 mins",
                "value": 97
              },
              "end_location": {
                "lat": 53.608335,
                "lng": -2.1478092
              },
              "html_instructions": "At the roundabout, take the <b>1st</b> exit onto <b>Crawford St</b>",
              "maneuver": "roundabout-left",
              "polyline": {
                "points": "_pefIlr`L?BAB?B?@A@ABA@BhBD`D@tCBfC?hC?`B?`A@v@?L@Lv@jJz@hKJrADx@B\\Df@"
              },
              "start_location": {
                "lat": 53.6091241,
                "lng": -2.1381504
              },
              "travel_mode": "DRIVING"
            },
            {
              "distance": {
                "text": "0.5 km",
                "value": 456
              },
              "duration": {
                "text": "1 min",
                "value": 75
              },
              "end_location": {
                "lat": 53.60927460000001,
                "lng": -2.1544229
              },
              "html_instructions": "Continue onto <b>Durham St</b>/<b>B6224</b>",
              "polyline": {
                "points": "ckefIxnbLVrB@N?JAN[~CUxBUzBYxCWjCQhBs@xGQhA"
              },
              "start_location": {
                "lat": 53.608335,
                "lng": -2.1478092
              },
              "travel_mode": "DRIVING"
            },
            {
              "distance": {
                "text": "50 m",
                "value": 50
              },
              "duration": {
                "text": "1 min",
                "value": 14
              },
              "end_location": {
                "lat": 53.609019,
                "lng": -2.1550418
              },
              "html_instructions": "Turn <b>left</b> onto <b>Miall St</b>/<b>B6224</b>",
              "maneuver": "turn-left",
              "polyline": {
                "points": "}pefIbxcLp@zB"
              },
              "start_location": {
                "lat": 53.60927460000001,
                "lng": -2.1544229
              },
              "travel_mode": "DRIVING"
            },
            {
              "distance": {
                "text": "0.2 km",
                "value": 187
              },
              "duration": {
                "text": "1 min",
                "value": 37
              },
              "end_location": {
                "lat": 53.610161,
                "lng": -2.1569126
              },
              "html_instructions": "Turn <b>right</b> onto <b>Milkstone Rd</b>/<b>B6224</b><div style=\"font-size:0.9em\">Go through 1 roundabout</div>",
              "maneuver": "turn-right",
              "polyline": {
                "points": "koefI~{cLo@p@Y\\KNO\\_@~@@@?@?@@??@?@?@?@?@?@A??@?@?@A??@?@A?A??@A?A?A?Il@CLOj@EJINKJEBC@A?MB"
              },
              "start_location": {
                "lat": 53.609019,
                "lng": -2.1550418
              },
              "travel_mode": "DRIVING"
            },
            {
              "distance": {
                "text": "0.5 km",
                "value": 524
              },
              "duration": {
                "text": "2 mins",
                "value": 94
              },
              "end_location": {
                "lat": 53.6088958,
                "lng": -2.1645165
              },
              "html_instructions": "Turn <b>left</b> onto <b>Tweedale St</b>",
              "maneuver": "turn-left",
              "polyline": {
                "points": "ovefItgdLTzBt@lGBN`@tD^bD^lD\\lDBVXbCJt@@`@BT?L@d@?`@E`A"
              },
              "start_location": {
                "lat": 53.610161,
                "lng": -2.1569126
              },
              "travel_mode": "DRIVING"
            },
            {
              "distance": {
                "text": "0.8 km",
                "value": 809
              },
              "duration": {
                "text": "2 mins",
                "value": 111
              },
              "end_location": {
                "lat": 53.6037787,
                "lng": -2.1725721
              },
              "html_instructions": "Turn <b>left</b> onto <b>Manchester Rd</b>/<b>A58</b>",
              "maneuver": "turn-left",
              "polyline": {
                "points": "snefIfweLh@L\\NVJNHXLp@`@f@\\VPh@b@^\\Z\\b@b@PTz@~@^b@f@p@NRd@t@t@tAP\\LVN`@Xp@Pd@^lAn@zBj@`CR`AXnAVjAv@lDDLLh@Ld@"
              },
              "start_location": {
                "lat": 53.6088958,
                "lng": -2.1645165
              },
              "travel_mode": "DRIVING"
            },
            {
              "distance": {
                "text": "0.7 km",
                "value": 667
              },
              "duration": {
                "text": "1 min",
                "value": 79
              },
              "end_location": {
                "lat": 53.60017560000001,
                "lng": -2.1657317
              },
              "html_instructions": "Turn <b>left</b> onto <b>Edinburgh Way</b>/<b>A664</b>",
              "maneuver": "turn-left",
              "polyline": {
                "points": "sndfIpigLfB~@LIPONQPYN]L]HWH]F_@Hq@Hy@Fy@Fs@Dw@Hk@De@JeAHs@He@F[Jk@Ha@Nk@Lc@Tq@Vs@P]P[Tc@Zi@l@cAR[`@i@PW\\_@Xa@b@o@"
              },
              "start_location": {
                "lat": 53.6037787,
                "lng": -2.1725721
              },
              "travel_mode": "DRIVING"
            },
            {
              "distance": {
                "text": "1.6 km",
                "value": 1598
              },
              "duration": {
                "text": "2 mins",
                "value": 91
              },
              "end_location": {
                "lat": 53.58778299999999,
                "lng": -2.1572162
              },
              "html_instructions": "Turn <b>right</b> onto <b>A627(M)</b>",
              "maneuver": "turn-right",
              "polyline": {
                "points": "cxcfIx~eLP_@Nb@t@`Af@p@LPXZZZRNNHTFJBN@V@R?f@ALAHAVC\\I`@I\\Ip@Qn@Sb@M`@M^Of@QTIf@Qb@Qh@W^Qd@Wh@U`@Ul@]h@[h@]h@_@j@]l@e@j@a@b@[p@m@~@w@r@o@bA_AbAeAh@o@f@o@bAqAv@kAhAaB`A{A`@s@b@u@tA{BhAeBf@u@hA{Ad@o@X]JSFMBKJ]J_@"
              },
              "start_location": {
                "lat": 53.60017560000001,
                "lng": -2.1657317
              },
              "travel_mode": "DRIVING"
            },
            {
              "distance": {
                "text": "0.9 km",
                "value": 869
              },
              "duration": {
                "text": "1 min",
                "value": 81
              },
              "end_location": {
                "lat": 53.5858152,
                "lng": -2.1663798
              },
              "html_instructions": "At <b>Thornham Interchange</b>, take the <b>3rd</b> exit onto the <b>M62</b> slip road to <b>Manchester</b>/<b>M'cr Airport</b>/<b>Bury</b>/<b>Botton</b>/<b>Liverpool</b>/<b>M66</b>/<b>M61</b>",
              "maneuver": "roundabout-left",
              "polyline": {
                "points": "sjafIridLDq@FSDKJUPQVUr@s@RQLGNGFAPALBTLPLHJHNPz@Lv@V~ANdALdAF|@I~@@~@Dr@LxAPxBJlBDvAB~ABjAArB?tACjBAhA?NArB?bBClBAf@AHOt@"
              },
              "start_location": {
                "lat": 53.58778299999999,
                "lng": -2.1572162
              },
              "travel_mode": "DRIVING"
            },
            {
              "distance": {
                "text": "8.1 km",
                "value": 8092
              },
              "duration": {
                "text": "6 mins",
                "value": 379
              },
              "end_location": {
                "lat": 53.54764650000001,
                "lng": -2.2662863
              },
              "html_instructions": "Merge onto <b>M62</b>",
              "maneuver": "merge",
              "polyline": {
                "points": "k~`fIzbfLIdGI~CEzBCdB?tA?tABfB@`ABtAFpAFnAHjADl@Dj@PdBLjAHn@Fj@V`BHh@VvAb@bCTxAVxAr@`FXvBV~BVdCPrBTrCJfBFz@FlAPzDf@nMPjDNbCVhDPnBPlBPfBZnCX|Bh@vDV~AFZb@hCRdAP~@`@fB^~AR|@j@zB^rAh@nB@DTr@Pl@p@vBb@tA\\|@Z~@b@fAb@hA\\z@Zv@b@~@Rd@Tb@lAdCz@hBlAfC~@xBdAbCjAtCx@rB~@bCz@~BdAvCv@zBpAzDl@nBl@lB`AfDl@rBh@tB|A~F|AvGBJf@tB`@nB`BzHz@jEn@hD|@vFTvATxAPfAPbA`@zB`@zBb@tBZzAHb@R|@f@|B^bBXfAXlAVdAZjAh@vB`@vA^pA|@bDz@lC\\hAh@`Bd@xAbAtCrAnD\\|@j@zAtA~CbB|DpArCp@xAHPbArBr@vAv@xA`AdBp@lA~@~Af@z@|AfCzAxBnAhBnA`BjA|AdArAdAlAz@`A`AhAhAlAfAlA~@`Ax@x@pB~B`BvBhB~B~@tAhAdBj@z@\\h@|@~AbAfBx@|An@tARb@v@|A~@pBv@`Bd@jABFr@`Bb@|@xAvDhArC|@`C`AnC`AvC`@nAhB|Fr@|Bb@|Al@|Bt@lCt@rCvA|FpAzF"
              },
              "start_location": {
                "lat": 53.5858152,
                "lng": -2.1663798
              },
              "travel_mode": "DRIVING"
            },
            {
              "distance": {
                "text": "1.4 km",
                "value": 1389
              },
              "duration": {
                "text": "1 min",
                "value": 68
              },
              "end_location": {
                "lat": 53.5412943,
                "lng": -2.2842781
              },
              "html_instructions": "Continue onto <b>M60</b>",
              "polyline": {
                "points": "yoyeIhsyLj@fCh@fCf@hCd@dCVxA`@|Bj@dDp@nDh@tCf@|B\\dBtAjGn@lCvA`Gr@hCbAxDPn@z@xCtAtEz@rCf@xAx@dCz@zBx@dB|@nB"
              },
              "start_location": {
                "lat": 53.54764650000001,
                "lng": -2.2662863
              },
              "travel_mode": "DRIVING"
            },
            {
              "distance": {
                "text": "0.4 km",
                "value": 375
              },
              "duration": {
                "text": "1 min",
                "value": 38
              },
              "end_location": {
                "lat": 53.5387757,
                "lng": -2.2879954
              },
              "html_instructions": "At junction <b>17</b>, take the <b>A56</b> exit to <b>M'cr city centre</b>/<b>Prestwich</b>/<b>Whitefield</b>",
              "maneuver": "ramp-left",
              "polyline": {
                "points": "ahxeIvc}L`@VPTjArB`@r@b@r@r@pAp@tArAdCLTZn@j@pA^V"
              },
              "start_location": {
                "lat": 53.5412943,
                "lng": -2.2842781
              },
              "travel_mode": "DRIVING"
            },
            {
              "distance": {
                "text": "6.8 km",
                "value": 6783
              },
              "duration": {
                "text": "16 mins",
                "value": 941
              },
              "end_location": {
                "lat": 53.4853811,
                "lng": -2.246857
              },
              "html_instructions": "At the roundabout, take the <b>1st</b> exit onto <b>Bury New Rd</b>/<b>A56</b><div style=\"font-size:0.9em\">Continue to follow A56</div><div style=\"font-size:0.9em\">Parts of this road may be closed at certain times or on certain days</div>",
              "maneuver": "roundabout-left",
              "polyline": {
                "points": "kxweI~z}LRD?@HBFDLJr@RVJTDTBR@TAn@I`@MZKRKTO`Ag@PINKpCaBbAi@`@GhAs@v@g@j@]l@]`@W|@k@bAk@\\Wb@[JMz@u@Z]ZYf@g@`@_@pAgAx@u@lAkAPQ|@w@XYjAgAz@y@dAeAd@e@VWNMbCcC^]TU`AcANOh@g@|@{@NMNO^[zBuB`C}B|AsA^_@DS@C@CHIRQ|@_ARUj@o@TUFGj@q@x@{@zBcCpAcANIXIf@i@`@c@JS`A}Ar@uAv@iAj@s@d@e@^WTKTOf@Yb@SbD{@zBe@x@STA^K`AYZOh@]b@[XSNQh@k@jA_BdAoAX_@n@u@d@o@v@gARW\\g@DG|@iBP_@Tm@Vs@N_@t@oBb@gA\\}@`AgCZw@\\y@b@eABGR_@LSPUPSXWTOp@Sp@OfAS~A]j@Mz@Sp@QVKp@[HElBaAbAi@@?jAs@PMHQZYz@e@dBy@R@F@`Ae@hAk@HEtBiAnCuAzAu@nCyAlBcAj@]DCXQXQROZYZ]`B}Al@g@JKpAmAdDqCn@i@j@i@hAcAX[ZYNQb@a@v@s@LM`@_@d@c@dAcAv@w@dCwBZY^]r@q@l@m@v@u@NQf@g@`AeAd@_@dA{@XSJIz@q@DC`A}@z@s@z@s@RO~AuArByAf@a@RQPOjBkBd@g@Z[JIJIp@c@hAu@j@]BAv@e@FELIJK`@c@DABEb@[b@_@HKRSTQNKFAD?L?JETMHCLGHEJIf@_@pBaAN?H@j@BZ@H?D@@@@@DDBDFVBL?L?BbA~BZv@Pb@HPRh@L\\HZ"
              },
              "start_location": {
                "lat": 53.5387757,
                "lng": -2.2879954
              },
              "travel_mode": "DRIVING"
            },
            {
              "distance": {
                "text": "0.1 km",
                "value": 128
              },
              "duration": {
                "text": "1 min",
                "value": 34
              },
              "end_location": {
                "lat": 53.4846248,
                "lng": -2.2454287
              },
              "html_instructions": "Turn <b>left</b> onto <b>Victoria Bridge St</b>/<b>A56</b>",
              "maneuver": "turn-left",
              "polyline": {
                "points": "sjmeIzyuLNONSHOHQJUJUZ_A^}@Nm@"
              },
              "start_location": {
                "lat": 53.4853811,
                "lng": -2.246857
              },
              "travel_mode": "DRIVING"
            },
            {
              "distance": {
                "text": "0.3 km",
                "value": 312
              },
              "duration": {
                "text": "2 mins",
                "value": 121
              },
              "end_location": {
                "lat": 53.4820301,
                "lng": -2.2472086
              },
              "html_instructions": "Turn <b>right</b> onto <b>Deansgate</b>/<b>A56</b><div style=\"font-size:0.9em\">May be closed at certain times or on certain days</div>",
              "maneuver": "turn-right",
              "polyline": {
                "points": "{emeI|puLh@`@t@`@`B~@h@`@rAz@VNXPrC~A"
              },
              "start_location": {
                "lat": 53.4846248,
                "lng": -2.2454287
              },
              "travel_mode": "DRIVING"
            },
            {
              "distance": {
                "text": "0.2 km",
                "value": 178
              },
              "duration": {
                "text": "1 min",
                "value": 79
              },
              "end_location": {
                "lat": 53.48170469999999,
                "lng": -2.2445936
              },
              "html_instructions": "Turn <b>left</b> onto <b>St Ann St</b>",
              "maneuver": "turn-left",
              "polyline": {
                "points": "uuleI`|uLT{ALwBBw@Bm@@o@HwAHiA"
              },
              "start_location": {
                "lat": 53.4820301,
                "lng": -2.2472086
              },
              "travel_mode": "DRIVING"
            },
            {
              "distance": {
                "text": "70 m",
                "value": 70
              },
              "duration": {
                "text": "1 min",
                "value": 31
              },
              "end_location": {
                "lat": 53.48108509999999,
                "lng": -2.2448019
              },
              "html_instructions": "Turn <b>right</b> onto <b>Cross St</b>/<b>A6042</b>",
              "maneuver": "turn-right",
              "polyline": {
                "points": "ssleItkuLrAZd@L"
              },
              "start_location": {
                "lat": 53.48170469999999,
                "lng": -2.2445936
              },
              "travel_mode": "DRIVING"
            },
            {
              "distance": {
                "text": "0.2 km",
                "value": 153
              },
              "duration": {
                "text": "1 min",
                "value": 45
              },
              "end_location": {
                "lat": 53.4808139,
                "lng": -2.2425292
              },
              "html_instructions": "<b>Cross St</b>/<b>A6042</b> turns <b>left</b> and becomes <b>King St</b>",
              "polyline": {
                "points": "yoleI~luLH}@H_A@UBWFmA?G@M?GPyC@S"
              },
              "start_location": {
                "lat": 53.48108509999999,
                "lng": -2.2448019
              },
              "travel_mode": "DRIVING"
            },
            {
              "distance": {
                "text": "7 m",
                "value": 7
              },
              "duration": {
                "text": "1 min",
                "value": 11
              },
              "end_location": {
                "lat": 53.4807512,
                "lng": -2.2425604
              },
              "html_instructions": "Turn <b>right</b> onto <b>Brown St</b>",
              "maneuver": "turn-right",
              "polyline": {
                "points": "anleIx~tLJD"
              },
              "start_location": {
                "lat": 53.4808139,
                "lng": -2.2425292
              },
              "travel_mode": "DRIVING"
            }
          ],
          "traffic_speed_entry": [],
          "via_waypoint": [
            {
              "location": {
                "lat": 53.8007526,
                "lng": -1.5490771
              },
              "step_index": 32,
              "step_interpolation": 0.01141182318527086
            },
            {
              "location": {
                "lat": 53.6097073,
                "lng": -2.156136
              },
              "step_index": 50,
              "step_interpolation": 0.5857813767717439
            }
          ]
        }
      ],
      "overview_polyline": {
        "points": "u_kyH`_XyNju@up@~f@w^lTwC`f@{c@piAo`@{Esi@d{@}Xl`@msA~qBoRxl@si@nWwj@jy@|KfV~@jfAm[`]sdAwAio@cFykAry@{fCbnBu`@zd@aGzu@fH`sDkbAh`EolAfw@koAhtCm{@rb@sgBlDkyEz}A{bCtpC_aAf@enCe\\gpG~q@{jCx]gbAjhAegCrxDozB`|AwmA|y@kqBvm@u}@p`@ol@n|@{v@v}@etA`U{sBvrAe{A`yAgh@vyAezBzzMw~C`xKqzAlsDqpA|iBmzA`fCadAhlCejCrjE{sAbmAkwC|oEkmCnnFabAtwDmeA|xDamA~tI{gApqDinBbxD{jApYspCdgCscCf~Bqr@nr@qiB|x@mvBna@u_Cz_AseEpfB_lAfi@kkAnEmdBeCizDqDyvAqQczBuoAqpBjc@q_A~WytAfNypBd}@qfAiRutAlKabFppD}iApyB_aArjDmhAbzAuuAnU}xA|EyhA_b@_zAwWkxAcd@c{AgN_fA`QgzAny@kiC`xBck@bBo~A{k@axAeReiC~_A{{ArScqAgaAi|AlEqaBzAsu@mf@sf@miA}cAmf@skC}oCem@il@}kAkvA}gAbTyjAf{@eeE|kA{dAr`AuhAhiBmoCnuDyt@dtAojA|h@qiAu\\k{@hJ{fByXutB{LogDaPejAlKifAdj@w}AnJkx@kTe~@ynAgxAqvAslGc`C}bBbScg@l]gj@{Ag~B_f@{oBq]wy@hi@qVxfAeFjqHi@n}Dqq@hoBmqA`{AytBfdDonAz{@weBzr@}~ClvBkjBlrBkbAyJcdAxhA_~A~xA{q@rvAq|@bbAw`@~Gaq@kTafAA}j@xt@{{@hc@{kAmOcw@ct@_y@_OsjAa|@}m@zE}aChtCccCzNaoAerAi}@ocCk{@i`AkzA|b@m}@{Rcw@S{Wp_@iR`bCwd@kMe\\ve@oFpAcH`U_QoLoj@xFgItNgRaMmIwi@iOxl@lYzi@zj@xcAl_AfP|X[M`^ho@r|AxqA~vB|cA`wA|Ll{@vGnoEbKpmD}Sp_Cpe@n`AxjAbcAl`@~j@fq@lWjhAoJti@h_Avr@`w@lXxdCrcArpHlpBjwGvw@brBwJrfCrGn~Cvq@j|EdbAlyKlHppDfc@|mA|m@t_@`k@~pAxVbj@gCpZsB~o@{m@d|AsB`oB|TnaAfMt`@bHaH~SsWhgAq~@rR`lC|UjtBlr@xpBxe@jrBndAp_BjeB~kFjvAq`AvmAktAvfBuiAry@ei@nHdBvQuE|DuK"
      },
      "summary": "M1",
      "warnings": [],
      "waypoint_order": []
    }
  ],
  "status": "OK"
}